[{"text": ["With God's wrath laden, Grendel came."], "index": 1, "start": 102800, "end": 106333}, {"text": ["The monster was minded of mankind now sundry to seize in the stately house."], "index": 2, "start": 106333, "end": 111066}, {"text": ["Under welkin he walked, till the wine-palace there, gold-hall of men,"], "index": 3, "start": 111066, "end": 115500}, {"text": ["he gladly discerned, flashing with fretwork."], "index": 4, "start": 115500, "end": 119000}, {"text": ["Not the first time, this, that he the home of Hrothgar sought,"], "index": 5, "start": 119000, "end": 121566}, {"text": ["yet ne'er in his life-day, late or early,"], "index": 6, "start": 122666, "end": 125866}, {"text": ["such hearty heroes, such hall-thanes found."], "index": 7, "start": 125866, "end": 129800}, {"text": ["Miss Yurikusa, please continue with page 8."], "index": 8, "start": 129800, "end": 131700}, {"text": ["Miss Yurikusa?"], "index": 9, "start": 132766, "end": 134000}, {"text": ["- [Snoring] - Miss Yurikusa, anytime now."], "index": 10, "start": 135766, "end": 137966}, {"text": ["- Come on. - Chika! Wake up!"], "index": 11, "start": 137966, "end": 139166}, {"text": ["Uh, huh?"], "index": 12, "start": 139900, "end": 141133}, {"text": ["Is class over?"], "index": 13, "start": 141133, "end": 142100}, {"text": ["[Yawn] I'm so tired..."], "index": 14, "start": 144333, "end": 147900}, {"text": ["Miss Yurikusa, please see me in my office after class."], "index": 15, "start": 147900, "end": 150600}, {"text": ["Chika, look at this test from last week."], "index": 16, "start": 154000, "end": 156100}, {"text": ["Mmm..."], "index": 17, "start": 156100, "end": 157533}, {"text": ["What's the problem here?"], "index": 18, "start": 157533, "end": 159700}, {"text": ["I just don't understand this stuff."], "index": 19, "start": 159700, "end": 162633}, {"text": ["[Groan] Chika. At this rate, you're going to fail my class."], "index": 20, "start": 162633, "end": 166833}, {"text": ["- But... - But nothing!"], "index": 21, "start": 166833, "end": 168833}, {"text": ["[Sigh]"], "index": 22, "start": 169800, "end": 171666}, {"text": ["Come to my room after school for tutoring."], "index": 23, "start": 171666, "end": 174066}, {"text": ["- Huh!? - Be there or you'll fail."], "index": 24, "start": 174066, "end": 176133}, {"text": ["I got it! I got it right here!"], "index": 25, "start": 176133, "end": 177600}, {"text": ["I got it right here!"], "index": 26, "start": 177600, "end": 179000}, {"text": ["- Get the ball! - Slide! Slide!"], "index": 27, "start": 179000, "end": 180966}, {"text": ["\"To be... To be a wol... To be a wolf, not...\""], "index": 28, "start": 187200, "end": 192733}, {"text": ["\"The glory was given, and...\""], "index": 29, "start": 192733, "end": 195600}, {"text": ["\"The glory was driven and Grendool... Grandma...\""], "index": 30, "start": 195600, "end": 200300}, {"text": ["\"And Grendel, thence deathsick in his den...\""], "index": 31, "start": 200300, "end": 202733}, {"text": ["\"In the dark moooo...\""], "index": 32, "start": 202733, "end": 206100}, {"text": ["\"The dark moor sought.\""], "index": 33, "start": 206100, "end": 208100}, {"text": ["\"The dark lord thought...\""], "index": 34, "start": 208100, "end": 210266}, {"text": ["[Tired groan]"], "index": 35, "start": 210266, "end": 211333}, {"text": ["Stop, no more..."], "index": 36, "start": 211333, "end": 212800}, {"text": ["What do you mean, no more?"], "index": 37, "start": 212800, "end": 214700}, {"text": ["We'll do this until you get it right."], "index": 38, "start": 214700, "end": 216200}, {"text": ["- I can't! - Yes, you can."], "index": 39, "start": 216200, "end": 218266}, {"text": ["You just have to apply yourself."], "index": 40, "start": 218266, "end": 220300}, {"text": ["Remember the test? Don't you want to do better than this?"], "index": 41, "start": 220300, "end": 222700}, {"text": ["I guess..."], "index": 42, "start": 222700, "end": 223866}, {"text": ["You guess?!"], "index": 43, "start": 223866, "end": 224966}, {"text": ["Come on, Chika!"], "index": 44, "start": 224966, "end": 226533}, {"text": ["Sorry I'm late!"], "index": 45, "start": 229000, "end": 230300}, {"text": ["Hey, Yuzu!"], "index": 46, "start": 230300, "end": 231233}, {"text": ["Where's Chika?"], "index": 47, "start": 232300, "end": 233766}, {"text": ["Classics tutoring."], "index": 48, "start": 233766, "end": 236566}, {"text": ["With Kurako, it's more like intensive training in classical literature."], "index": 49, "start": 236566, "end": 239200}, {"text": ["Oh no! Poor Chika, huh?"], "index": 50, "start": 239200, "end": 243266}, {"text": ["Yeah, I know. She's the only one in her entire class that needs to be tutored!"], "index": 51, "start": 243266, "end": 247066}, {"text": ["Oh, well, I mean, I'm not doing too well either."], "index": 52, "start": 247066, "end": 250333}, {"text": ["Miss Kurako is an amazing teacher."], "index": 53, "start": 250333, "end": 253366}, {"text": ["But she cares enough to tutor Chika after class?"], "index": 54, "start": 253366, "end": 255933}, {"text": ["I think it's really great."], "index": 55, "start": 255933, "end": 257000}, {"text": ["I wonder how long they'll be able to keep at it."], "index": 56, "start": 259433, "end": 261066}, {"text": ["Huh?"], "index": 57, "start": 261066, "end": 262933}, {"text": ["Well, with Chika and Kurako, it's like oil and water, right?"], "index": 58, "start": 262933, "end": 265366}, {"text": ["And Chika can be pretty rude."], "index": 59, "start": 266400, "end": 268233}, {"text": ["Oh, it won't be so bad."], "index": 60, "start": 268233, "end": 269600}, {"text": ["Or... will it?"], "index": 61, "start": 270833, "end": 272100}, {"text": ["\"By the gate of the graceless foe...\""], "index": 62, "start": 274900, "end": 276166}, {"text": ["\"The great of the faceless dough have a... weary...\""], "index": 63, "start": 279233, "end": 283166}, {"text": ["\"The weary-hearted, away from thence-\""], "index": 64, "start": 283166, "end": 286600}, {"text": ["\"A wormy-hearted, away from a fence...\""], "index": 65, "start": 286600, "end": 289166}, {"text": ["[Exhausted groan]"], "index": 66, "start": 290466, "end": 293100}, {"text": ["[Resigned groan]"], "index": 67, "start": 293100, "end": 295066}, {"text": ["Come on. You're doing this on purpose."], "index": 68, "start": 296766, "end": 299866}, {"text": ["I couldn't even if I tried."], "index": 69, "start": 299866, "end": 301666}, {"text": ["Dammit!"], "index": 70, "start": 307733, "end": 309766}, {"text": ["I cannot get any closer in this weak little body."], "index": 71, "start": 309766, "end": 312300}, {"text": ["We're so close, my children."], "index": 72, "start": 313633, "end": 315800}, {"text": ["The realm of reality is so close."], "index": 73, "start": 315800, "end": 317900}, {"text": ["But it's not nearly close enough."], "index": 74, "start": 319333, "end": 322066}, {"text": ["We need her. The priestess."], "index": 75, "start": 322066, "end": 325700}, {"text": ["Hurry! Without her, I will never become manifest."], "index": 76, "start": 325700, "end": 328066}, {"text": ["I know, Master."], "index": 77, "start": 328066, "end": 329366}, {"text": ["Ayatachi..."], "index": 78, "start": 330033, "end": 331066}, {"text": ["Yes."], "index": 79, "start": 331733, "end": 334033}, {"text": ["Soon I will return you. Your time is almost up."], "index": 80, "start": 334033, "end": 338633}, {"text": ["- [Shocked gasp] - [Giggle]"], "index": 81, "start": 338633, "end": 340566}, {"text": ["Have I asked too much of you, Ayatachi?"], "index": 82, "start": 340566, "end": 343133}, {"text": ["Do you hate me now?"], "index": 83, "start": 343133, "end": 344600}, {"text": ["He's finally gone."], "index": 84, "start": 348166, "end": 349666}, {"text": ["[Exhausted panting]"], "index": 85, "start": 352133, "end": 355533}, {"text": ["Oh, um, uh, Ayatachi?"], "index": 86, "start": 355533, "end": 357800}, {"text": ["Are you okay?"], "index": 87, "start": 358566, "end": 359433}, {"text": ["- Huh? - [Gasp]"], "index": 88, "start": 363033, "end": 364166}, {"text": ["Kusugi!"], "index": 89, "start": 370366, "end": 371800}, {"text": ["Huh? Amatsu?"], "index": 90, "start": 371800, "end": 373300}, {"text": ["What is all that stuff?"], "index": 91, "start": 374333, "end": 376600}, {"text": ["Would you mind helping me out with something?"], "index": 92, "start": 376600, "end": 378300}, {"text": ["Huh?"], "index": 93, "start": 378300, "end": 379300}, {"text": ["They were having a sale on curry bread,"], "index": 94, "start": 381400, "end": 383333}, {"text": ["and I guess I went a little out of control."], "index": 95, "start": 383333, "end": 385266}, {"text": ["A little out of control?!"], "index": 96, "start": 385266, "end": 386900}, {"text": ["But it was half-off!"], "index": 97, "start": 386900, "end": 387900}, {"text": ["That's no reason to buy more than you can eat by yourself."], "index": 98, "start": 389666, "end": 392966}, {"text": ["Shut up. I know it was stupid, but now you get to eat some free bread."], "index": 99, "start": 392966, "end": 395866}, {"text": ["Yeah, I guess you are related to that klutz, Yuzu."], "index": 100, "start": 397833, "end": 400033}, {"text": ["Uh, I don't really feel the need to deny that one."], "index": 101, "start": 401766, "end": 404133}, {"text": ["You okay?"], "index": 102, "start": 410833, "end": 411966}, {"text": ["Huh?"], "index": 103, "start": 411966, "end": 413500}, {"text": ["Oh, no. It's nothing."], "index": 104, "start": 413500, "end": 415366}, {"text": ["You sure?"], "index": 105, "start": 416300, "end": 417466}, {"text": ["Yeah. That curry bread..."], "index": 106, "start": 417466, "end": 419400}, {"text": ["Too spicy for me."], "index": 107, "start": 421000, "end": 422266}, {"text": ["Hmph!"], "index": 108, "start": 437366, "end": 438266}, {"text": ["Finally, I'm free of Kurako and stupid classics."], "index": 109, "start": 441733, "end": 444566}, {"text": ["[Gulping, satisfied sigh]"], "index": 110, "start": 445500, "end": 448066}, {"text": ["What's her problem anyway?"], "index": 111, "start": 449500, "end": 451666}, {"text": ["It's probably because she's old"], "index": 112, "start": 451666, "end": 454700}, {"text": ["and she likes taking out her frustrations on us poor little students!"], "index": 113, "start": 454700, "end": 457566}, {"text": ["Border spirit!"], "index": 114, "start": 466000, "end": 466766}, {"text": ["Go on. Get to it."], "index": 115, "start": 469533, "end": 470700}, {"text": ["[Paper rustles]"], "index": 116, "start": 471700, "end": 475266}, {"text": ["[Gate rattles shut]"], "index": 117, "start": 483266, "end": 485200}, {"text": ["ALL: Huh?"], "index": 118, "start": 491500, "end": 492300}, {"text": ["What is it?! What's happening?!"], "index": 119, "start": 495200, "end": 496466}, {"text": ["[Strained grunts]"], "index": 120, "start": 499233, "end": 501366}, {"text": ["- It won't budge! - I can't open this either!"], "index": 121, "start": 501366, "end": 503066}, {"text": ["Get back, Seiko!"], "index": 122, "start": 503066, "end": 504033}, {"text": ["[Battle cry]"], "index": 123, "start": 505766, "end": 508066}, {"text": ["What do we do now?"], "index": 124, "start": 517933, "end": 520100}, {"text": ["They've trapped us inside with this border spell."], "index": 125, "start": 520100, "end": 521799}, {"text": ["[Leaves rustle]"], "index": 126, "start": 522933, "end": 524600}, {"text": ["Huh?"], "index": 127, "start": 527566, "end": 528633}, {"text": ["Wait, stop, where are you taking me?!"], "index": 128, "start": 530066, "end": 531566}, {"text": ["[Startled shouts]"], "index": 129, "start": 532466, "end": 535633}, {"text": ["Ow!"], "index": 130, "start": 539266, "end": 540866}, {"text": ["Stupid branch..."], "index": 131, "start": 540866, "end": 542400}, {"text": ["Huh?"], "index": 132, "start": 542400, "end": 544866}, {"text": ["[Startled gasp] What are those things?!"], "index": 133, "start": 544866, "end": 545866}, {"text": ["Those are..."], "index": 134, "start": 551633, "end": 552900}, {"text": ["Miss Kurako!"], "index": 135, "start": 553533, "end": 555233}, {"text": ["Miss Yurikusa, are you okay?"], "index": 136, "start": 555233, "end": 556900}, {"text": ["What's going on?"], "index": 137, "start": 556900, "end": 557800}, {"text": ["It's the enemy. They've set up a boundary spell."], "index": 138, "start": 559533, "end": 563033}, {"text": ["It looks like they've trapped the other girls inside."], "index": 139, "start": 563033, "end": 565400}, {"text": ["Come on! Die already!"], "index": 140, "start": 565400, "end": 566866}, {"text": ["Die! Die! Die! Die! Die!"], "index": 141, "start": 566866, "end": 569066}, {"text": ["The room's turning white."], "index": 142, "start": 569066, "end": 571100}, {"text": ["We need to get out of here before they cover everything."], "index": 143, "start": 571100, "end": 572233}, {"text": ["Yeah. If we can't get out soon, we'll be totally surrounded."], "index": 144, "start": 574500, "end": 576666}, {"text": ["[Startled grunt]"], "index": 145, "start": 580433, "end": 581866}, {"text": ["They're everywhere!"], "index": 146, "start": 581866, "end": 582666}, {"text": ["[Startled shout]"], "index": 147, "start": 587300, "end": 588666}, {"text": ["All right!"], "index": 148, "start": 592733, "end": 593900}, {"text": ["Huh?"], "index": 149, "start": 594533, "end": 595300}, {"text": ["[Leaves rustling] Huh?"], "index": 150, "start": 604800, "end": 607033}, {"text": ["They're all just clones."], "index": 151, "start": 607033, "end": 609800}, {"text": ["Maybe they'll all disappear if I hit the original."], "index": 152, "start": 609800, "end": 611466}, {"text": ["Wait. I have an idea."], "index": 153, "start": 613200, "end": 614433}, {"text": ["Huh?"], "index": 154, "start": 614433, "end": 615366}, {"text": ["[Magic hums]"], "index": 155, "start": 619333, "end": 621800}, {"text": ["Find it!"], "index": 156, "start": 621800, "end": 623066}, {"text": ["Right."], "index": 157, "start": 626333, "end": 627433}, {"text": ["That's it!"], "index": 158, "start": 634933, "end": 635866}, {"text": ["Kamuromina Hiya!"], "index": 159, "start": 637500, "end": 639933}, {"text": ["[Arrow whooshes]"], "index": 160, "start": 639933, "end": 641400}, {"text": ["[Relieved gasps]"], "index": 161, "start": 648466, "end": 649800}, {"text": ["Thank you for your help, Miss Yurikusa."], "index": 162, "start": 652700, "end": 654833}, {"text": ["- Chika! - Huh?"], "index": 163, "start": 654833, "end": 656333}, {"text": ["Miss Kurako!"], "index": 164, "start": 656333, "end": 658000}, {"text": ["Hey, guys!"], "index": 165, "start": 658000, "end": 659166}, {"text": ["Miss Kurako?"], "index": 166, "start": 661300, "end": 662500}, {"text": ["What is it?"], "index": 167, "start": 662500, "end": 664066}, {"text": ["I swear I'm gonna study real hard from now on."], "index": 168, "start": 664066, "end": 666133}, {"text": ["Oh! [Chuckles]"], "index": 169, "start": 666133, "end": 667666}, {"text": ["[Happy laughter]"], "index": 170, "start": 667666, "end": 670433}, {"text": ["Hey! Oh my God!"], "index": 171, "start": 672800, "end": 674833}, {"text": ["Oh my God! That was awesome!"], "index": 172, "start": 674833, "end": 676133}, {"text": ["[Exasperated sigh]"], "index": 173, "start": 686366, "end": 687033}, {"text": ["[Tired groan]"], "index": 174, "start": 688633, "end": 689633}, {"text": ["I know you're studying harder,"], "index": 175, "start": 691066, "end": 692633}, {"text": ["but you're doing even worse, Chika."], "index": 176, "start": 693733, "end": 696466}]