[{"text": ["Stupid bike!"], "index": 1, "start": 113024, "end": 114422}, {"text": ["Darn it!"], "index": 2, "start": 115221, "end": 116419}, {"text": ["Why didn't anyone wake me up?!"], "index": 3, "start": 118183, "end": 119881}, {"text": ["I can't believe they left without me!"], "index": 4, "start": 119881, "end": 121545}, {"text": ["I bet they think this is so funny, those idiots!"], "index": 5, "start": 121545, "end": 123476}, {"text": ["They're... so... dead!"], "index": 6, "start": 127104, "end": 129501}, {"text": ["Look, it's Kusugi!"], "index": 7, "start": 144447, "end": 145778}, {"text": ["Huh?"], "index": 8, "start": 145778, "end": 146976}, {"text": ["[Adoring sigh]"], "index": 9, "start": 154932, "end": 156862}, {"text": ["[Shy giggles]"], "index": 10, "start": 158926, "end": 160424}, {"text": ["[Startled gasp]"], "index": 11, "start": 165883, "end": 166948}, {"text": ["Hey, you're the-"], "index": 12, "start": 170011, "end": 171075}, {"text": ["[Pained grunt]"], "index": 13, "start": 171075, "end": 172241}, {"text": ["I made it on time!"], "index": 14, "start": 173971, "end": 176135}, {"text": ["Hey! Why didn't you wake me up?!"], "index": 15, "start": 176135, "end": 178799}, {"text": ["Is this your idea of a joke?! 'Cause it's not funny at all!"], "index": 16, "start": 178799, "end": 181395}, {"text": ["Because of you, I had to take this shortcut and then I-"], "index": 17, "start": 181395, "end": 183093}, {"text": ["- Huh? - Look."], "index": 18, "start": 183093, "end": 185190}, {"text": ["What do you mean? Look down?"], "index": 19, "start": 185190, "end": 187287}, {"text": ["[Choking gasp]"], "index": 20, "start": 187287, "end": 188751}, {"text": ["[Shocked yell]"], "index": 21, "start": 190448, "end": 192180}, {"text": ["I'm so sorry! Are you okay?!"], "index": 22, "start": 192180, "end": 193678}, {"text": ["You again with that bike!"], "index": 23, "start": 197672, "end": 198870}, {"text": ["Huh? Again?"], "index": 24, "start": 199902, "end": 201832}, {"text": ["Watch where you're going with that thing, you stupid brat!"], "index": 25, "start": 201832, "end": 203430}, {"text": ["You can't just run over everyone in the street!"], "index": 26, "start": 204795, "end": 207125}, {"text": ["Don't you know who I am?!"], "index": 27, "start": 207125, "end": 209489}, {"text": ["Did you see that?! It's like she never rode a bike before!"], "index": 28, "start": 209489, "end": 212517}, {"text": ["- Well, she'd better stay away from me... - Is he weird or what?"], "index": 29, "start": 212517, "end": 214415}, {"text": ["Well, you hit him with your bike, Yuzu."], "index": 30, "start": 216479, "end": 217411}, {"text": ["Because of the incident the other day in the auditorium,"], "index": 31, "start": 232956, "end": 235485}, {"text": ["the school has decided to recruit students"], "index": 32, "start": 235485, "end": 237449}, {"text": ["with potential to form a priestess club."], "index": 33, "start": 237449, "end": 238381}, {"text": ["There will be one student from each class."], "index": 34, "start": 240645, "end": 242442}, {"text": ["Just based on past experience, any volunteers?"], "index": 35, "start": 243907, "end": 247369}, {"text": ["Oh..."], "index": 36, "start": 248667, "end": 250065}, {"text": ["No way, Sis!"], "index": 37, "start": 251363, "end": 252995}, {"text": ["Kurako. Not \"Sis.\""], "index": 38, "start": 252995, "end": 255891}, {"text": ["Uh, oh yeah."], "index": 39, "start": 255891, "end": 257854}, {"text": ["Miss Kurako?"], "index": 40, "start": 257854, "end": 258587}, {"text": ["Yes, Miss Hieda?"], "index": 41, "start": 259718, "end": 261049}, {"text": ["Ahem."], "index": 42, "start": 262315, "end": 264479}, {"text": ["It's not fair! You can't make me join that club!"], "index": 43, "start": 264479, "end": 267574}, {"text": ["I'm proud to say that I've never been in any clubs"], "index": 44, "start": 267574, "end": 269904}, {"text": ["and I'm not going to let you change that now!"], "index": 45, "start": 269904, "end": 272567}, {"text": ["- Okay, Miss Hieda. I won't make you join. - Why does she have to be so weird?"], "index": 46, "start": 272567, "end": 274231}, {"text": ["- That's right! - Miss Kurako."], "index": 47, "start": 274231, "end": 275863}, {"text": ["Yes, Mr. Kusugi?"], "index": 48, "start": 275863, "end": 277394}, {"text": ["I might not have the most experience at fighting demons,"], "index": 49, "start": 279158, "end": 283118}, {"text": ["but I would think that it takes a certain amount of skill and coordination."], "index": 50, "start": 283118, "end": 286980}, {"text": ["Though I'm sure there are some very talented students at this school,"], "index": 51, "start": 286980, "end": 290009}, {"text": ["do you think they are really up to the task?"], "index": 52, "start": 290009, "end": 292972}, {"text": ["As the representative of the Inao Shrine, I will be the judge of that."], "index": 53, "start": 292972, "end": 296367}, {"text": ["The best weapon against evil is a pure soul"], "index": 54, "start": 296367, "end": 298431}, {"text": ["and I'm sure we have at least a few here."], "index": 55, "start": 298431, "end": 301093}, {"text": ["In fact, I believe that students will be the best qualified for this task."], "index": 56, "start": 301093, "end": 305287}, {"text": ["Sure, Miss Kurako."], "index": 57, "start": 305287, "end": 308117}, {"text": ["But a klutz who can't even ride a bike shouldn't be our class representative."], "index": 58, "start": 308117, "end": 310380}, {"text": ["Heh."], "index": 59, "start": 312777, "end": 314042}, {"text": ["[Annoyed growl]"], "index": 60, "start": 314042, "end": 316239}, {"text": ["Hey, Sis! I'll join that club!"], "index": 61, "start": 316239, "end": 318503}, {"text": ["I know I can do it!"], "index": 62, "start": 318503, "end": 319402}, {"text": ["[Exasperated sigh]"], "index": 63, "start": 326625, "end": 327390}, {"text": ["What?!"], "index": 64, "start": 332998, "end": 333631}, {"text": ["No one from the other classes has volunteered?!"], "index": 65, "start": 335528, "end": 338025}, {"text": ["Yeah, well, not quite the turnout I was hoping for."], "index": 66, "start": 338025, "end": 341685}, {"text": ["But I guess I shouldn't have expected anyone"], "index": 67, "start": 341685, "end": 344316}, {"text": ["to volunteer for a club to fight demons."], "index": 68, "start": 344316, "end": 345614}, {"text": ["So, wait. Do I still have to be in the club then?"], "index": 69, "start": 347444, "end": 350573}, {"text": ["What? But I didn't make you join."], "index": 70, "start": 350573, "end": 352138}, {"text": ["You volunteered."], "index": 71, "start": 352138, "end": 354235}, {"text": ["Oh! I didn't mean it!"], "index": 72, "start": 354235, "end": 358162}, {"text": ["Besides, I thought you had your own reasons for joining the club."], "index": 73, "start": 358162, "end": 360459}, {"text": ["Huh?"], "index": 74, "start": 360459, "end": 362024}, {"text": ["Won't you be protecting someone special?"], "index": 75, "start": 362024, "end": 363655}, {"text": ["Huh? Oh."], "index": 76, "start": 365053, "end": 366884}, {"text": ["Hiro will be in danger!"], "index": 77, "start": 369214, "end": 371144}, {"text": ["And I'm the only one who can protect him!"], "index": 78, "start": 371144, "end": 372642}, {"text": ["Anyway, I'm sure it will be fine."], "index": 79, "start": 376604, "end": 378501}, {"text": ["Fate always provides."], "index": 80, "start": 378501, "end": 381297}, {"text": ["You'll find people whose hearts and minds are in harmony with your own."], "index": 81, "start": 381297, "end": 383760}, {"text": ["Then you won't be the only one in your club."], "index": 82, "start": 383760, "end": 385291}, {"text": ["Did that monster hit you on the head one too many times?"], "index": 83, "start": 394945, "end": 397541}, {"text": ["Why would we want to join a club that fight demons?"], "index": 84, "start": 397541, "end": 398905}, {"text": ["Not if you paid me."], "index": 85, "start": 400203, "end": 401436}, {"text": ["You're sure? Really?"], "index": 86, "start": 405196, "end": 406594}, {"text": ["I guess I'm all alone then."], "index": 87, "start": 408459, "end": 409590}, {"text": ["Come on! You're my best friends!"], "index": 88, "start": 411322, "end": 413485}, {"text": ["And we're all in different homerooms!"], "index": 89, "start": 413485, "end": 414683}, {"text": ["Nuh-uh!"], "index": 90, "start": 414683, "end": 415881}, {"text": ["I see how it is."], "index": 91, "start": 419111, "end": 421873}, {"text": ["Cut the guilt, Yuzu. We didn't grow up in a shrine."], "index": 92, "start": 421873, "end": 423571}, {"text": ["We can't do it, okay?"], "index": 93, "start": 423571, "end": 424636}, {"text": ["What about all that \"girls have to stick together\" crap, huh?"], "index": 94, "start": 427432, "end": 429063}, {"text": ["[Soft sobbing]"], "index": 95, "start": 430195, "end": 432093}, {"text": ["Tears don't work on us, Yuzu."], "index": 96, "start": 432093, "end": 433624}, {"text": ["Hey."], "index": 97, "start": 442378, "end": 443776}, {"text": ["Oh, Kusugi."], "index": 98, "start": 443776, "end": 444941}, {"text": ["Hey."], "index": 99, "start": 444941, "end": 446039}, {"text": ["Headed home?"], "index": 100, "start": 447138, "end": 448603}, {"text": ["Uh-huh."], "index": 101, "start": 448603, "end": 449568}, {"text": ["Huh?"], "index": 102, "start": 450932, "end": 451598}, {"text": ["Not the best day for you, huh?"], "index": 103, "start": 453129, "end": 454927}, {"text": ["Huh? No thanks to her!"], "index": 104, "start": 454927, "end": 457158}, {"text": ["Are you gonna be okay?"], "index": 105, "start": 457158, "end": 457590}, {"text": ["I'm sorry. Yuzu-"], "index": 106, "start": 459055, "end": 460753}, {"text": ["Don't worry about it. Forget it."], "index": 107, "start": 460753, "end": 461717}, {"text": ["I heard you're staying with her."], "index": 108, "start": 463848, "end": 465312}, {"text": ["It's not true, is it, Hiro?"], "index": 109, "start": 465312, "end": 467309}, {"text": ["Well... Yeah, I am."], "index": 110, "start": 467309, "end": 470572}, {"text": ["But I think you've got Yuzu pegged all wrong."], "index": 111, "start": 470572, "end": 472869}, {"text": ["She's a klutz, but she really does mean well."], "index": 112, "start": 472869, "end": 475232}, {"text": ["I think she does..."], "index": 113, "start": 475232, "end": 476896}, {"text": ["But I can't really tell sometimes."], "index": 114, "start": 476896, "end": 478461}, {"text": ["[Sigh]"], "index": 115, "start": 478993, "end": 480957}, {"text": ["I can't believe you have to deal with that girl all the time."], "index": 116, "start": 480957, "end": 482622}, {"text": ["Dude, Yuzu's life really sucks, doesn't it?"], "index": 117, "start": 486050, "end": 488280}, {"text": ["I guess so..."], "index": 118, "start": 488280, "end": 490711}, {"text": ["Yeah, you're right. She gets to spend all"], "index": 119, "start": 490711, "end": 492708}, {"text": ["her high school living with her true love."], "index": 120, "start": 492708, "end": 494306}, {"text": ["I wish I had a true love."], "index": 121, "start": 494306, "end": 496069}, {"text": ["Never gonna happen."], "index": 122, "start": 496069, "end": 497268}, {"text": ["Thanks a lot, Chika."], "index": 123, "start": 497268, "end": 498865}, {"text": ["I gotta find me a boyfriend."], "index": 124, "start": 498865, "end": 500530}, {"text": ["Huh? What's up?"], "index": 125, "start": 500530, "end": 502627}, {"text": ["- Shhh! - Hey! What's your problem, Chika?!"], "index": 126, "start": 502627, "end": 504957}, {"text": ["- Let go of my arm! - Shut up, okay?"], "index": 127, "start": 504957, "end": 506588}, {"text": ["Oh, come on. You've got to be kidding me."], "index": 128, "start": 512646, "end": 514943}, {"text": ["You think Yuzu can protect this school?"], "index": 129, "start": 514943, "end": 516707}, {"text": ["What, she'll run demons over with her bike?"], "index": 130, "start": 516707, "end": 518272}, {"text": ["Oh, well, I guess you just don't really get along well with Yuzu, huh? [Chuckle]"], "index": 131, "start": 520269, "end": 523165}, {"text": ["Of course not! She's a-"], "index": 132, "start": 523165, "end": 525063}, {"text": ["[Pained groan]"], "index": 133, "start": 525063, "end": 526560}, {"text": ["Are you sure you're okay?"], "index": 134, "start": 526560, "end": 527892}, {"text": ["Yeah..."], "index": 135, "start": 527892, "end": 528558}, {"text": ["[Embarassed whimper]"], "index": 136, "start": 533151, "end": 534915}, {"text": ["Hey..."], "index": 137, "start": 534915, "end": 536612}, {"text": ["Okay, did you see that?! Did that really happen?!"], "index": 138, "start": 536612, "end": 538310}, {"text": ["It happened."], "index": 139, "start": 538310, "end": 539376}, {"text": ["Huh?"], "index": 140, "start": 542904, "end": 543603}, {"text": ["[Annoyed groan]"], "index": 141, "start": 548762, "end": 552025}, {"text": ["They're... Do you think they're really...?"], "index": 142, "start": 554621, "end": 555586}, {"text": ["[Contented sigh]"], "index": 143, "start": 559215, "end": 560579}, {"text": ["They really are!"], "index": 144, "start": 567170, "end": 568202}, {"text": ["It's in the picture."], "index": 145, "start": 569167, "end": 570066}, {"text": ["Mm-hmm."], "index": 146, "start": 570066, "end": 571530}, {"text": ["Chika, we... can't tell anyone."], "index": 147, "start": 572429, "end": 575558}, {"text": ["No one?"], "index": 148, "start": 576524, "end": 577389}, {"text": ["Oh, why can't I have one, a pretty one?! Just for once!"], "index": 149, "start": 578887, "end": 581849}, {"text": ["Y'know..."], "index": 150, "start": 581849, "end": 582782}, {"text": ["I know exactly what you mean!"], "index": 151, "start": 584612, "end": 586010}, {"text": ["There'll be drama."], "index": 152, "start": 587076, "end": 587841}, {"text": ["This is gonna be really, really good!"], "index": 153, "start": 589472, "end": 591070}, {"text": ["We must stick by you until the end!"], "index": 154, "start": 592434, "end": 593766}, {"text": ["We must!"], "index": 155, "start": 594865, "end": 596363}, {"text": ["A priestess club?"], "index": 156, "start": 603952, "end": 605051}, {"text": ["Yes. To help protect the school."], "index": 157, "start": 606382, "end": 609278}, {"text": ["Sounds really cool. Can I join?"], "index": 158, "start": 609278, "end": 611641}, {"text": ["No, you're too young."], "index": 159, "start": 611641, "end": 613005}, {"text": ["Why? I'm gonna be a priestess, too!"], "index": 160, "start": 614470, "end": 615935}, {"text": ["No, Tama!"], "index": 161, "start": 615935, "end": 618198}, {"text": ["Well, I think that's a wonderful idea."], "index": 162, "start": 618198, "end": 620762}, {"text": ["It's nice that you girls have something to keep you busy after school."], "index": 163, "start": 620762, "end": 622492}, {"text": ["But don't you think it's dangerous, sir?"], "index": 164, "start": 624489, "end": 625488}, {"text": ["I suppose..."], "index": 165, "start": 627186, "end": 628551}, {"text": ["But young men whose reason has been destroyed by raging hormones"], "index": 166, "start": 630615, "end": 633676}, {"text": ["are much more dangerous than any demon, don't you think?"], "index": 167, "start": 633676, "end": 636107}, {"text": ["Don't listen to Daddy."], "index": 168, "start": 636107, "end": 637139}, {"text": ["What do you mean?! You always listen to me, don't you?"], "index": 169, "start": 638669, "end": 640966}, {"text": ["When you talk about boys, we don't!"], "index": 170, "start": 640966, "end": 642764}, {"text": ["You're just being silly!"], "index": 171, "start": 642764, "end": 643796}, {"text": ["Silly?!"], "index": 172, "start": 643796, "end": 646026}, {"text": ["No one else volunteered, so I'll just be in the club by myself anyway."], "index": 173, "start": 646026, "end": 648423}, {"text": ["[Exasperated groan]"], "index": 174, "start": 650187, "end": 651785}, {"text": ["What?! You really mean it?!"], "index": 175, "start": 655180, "end": 656511}, {"text": ["Mm-hmm."], "index": 176, "start": 657777, "end": 659008}, {"text": ["You guys really want to join the Priestess Club with me?"], "index": 177, "start": 660706, "end": 663002}, {"text": ["Of course we do!"], "index": 178, "start": 663002, "end": 666198}, {"text": ["Our best friend needs our help and we need to be close we can see what-"], "index": 179, "start": 666198, "end": 669261}, {"text": ["I mean, we can support her in her hour of need!"], "index": 180, "start": 669261, "end": 671557}, {"text": ["Thank you, Seiko!"], "index": 181, "start": 671557, "end": 672889}, {"text": ["Yuzu!"], "index": 182, "start": 672889, "end": 674419}, {"text": ["[Happy squeal]"], "index": 183, "start": 674419, "end": 675418}, {"text": ["What's going on over there?"], "index": 184, "start": 678214, "end": 679479}, {"text": ["I got your back, bro."], "index": 185, "start": 683107, "end": 684872}, {"text": ["Huh?"], "index": 186, "start": 684872, "end": 685803}, {"text": ["I have the best friends in the whole world!"], "index": 187, "start": 692828, "end": 694458}]