[{"text": ["This'll be your room. Take a look."], "index": 1, "start": 102800, "end": 105233}, {"text": ["From now on, this will be your home."], "index": 2, "start": 107066, "end": 109266}, {"text": ["Do you remember this room at all?"], "index": 3, "start": 109933, "end": 111766}, {"text": ["Yeah, I remember. Vaguely."], "index": 4, "start": 111766, "end": 115933}, {"text": ["You and Yuzu used to play in here all the time when you were little."], "index": 5, "start": 115933, "end": 118700}, {"text": ["Yeah..."], "index": 6, "start": 119300, "end": 120566}, {"text": ["What's the matter? Aren't you hungry?"], "index": 7, "start": 129166, "end": 131200}, {"text": ["Yes, it looks great."], "index": 8, "start": 131200, "end": 133133}, {"text": ["We're gonna get to see Hiro every day!"], "index": 9, "start": 133133, "end": 134933}, {"text": ["Tama, he's just here for high school."], "index": 10, "start": 135533, "end": 137366}, {"text": ["I know. I didn't say forever."], "index": 11, "start": 137366, "end": 139533}, {"text": ["It's great you got here in time for the ceremony for the freshmen."], "index": 12, "start": 140233, "end": 142933}, {"text": ["Yeah, you should've seen it."], "index": 13, "start": 143700, "end": 145766}, {"text": ["Yuzu was sooo worried that you wouldn't get here in time"], "index": 14, "start": 145766, "end": 149100}, {"text": ["and you wouldn't be able to go to the ceremony together."], "index": 15, "start": 149100, "end": 151033}, {"text": ["Ewww, Yuzu! Yuck!"], "index": 16, "start": 151033, "end": 152466}, {"text": ["Go clean yourself up, Yuzu."], "index": 17, "start": 153866, "end": 155600}, {"text": ["You got soup all over the-"], "index": 18, "start": 155600, "end": 156433}, {"text": ["Yeah, um..."], "index": 19, "start": 156433, "end": 157466}, {"text": ["Huh?"], "index": 20, "start": 157466, "end": 158133}, {"text": ["Th-That thing that attacked me this afternoon..."], "index": 21, "start": 160366, "end": 163366}, {"text": ["It's just that I-I felt like he knew me."], "index": 22, "start": 167066, "end": 170233}, {"text": ["And... this happens a lot."], "index": 23, "start": 171266, "end": 174766}, {"text": ["Ever since I can remember, bad things happen around me."], "index": 24, "start": 174766, "end": 177133}, {"text": ["I just want to know. Why me?"], "index": 25, "start": 180333, "end": 182733}, {"text": ["I think you're ready."], "index": 26, "start": 184833, "end": 185866}, {"text": ["For what?"], "index": 27, "start": 186766, "end": 189366}, {"text": ["Yes. I should have seen it before, but it's still not clear."], "index": 28, "start": 189366, "end": 193366}, {"text": ["All I know is something is about to happen, which will change your destiny."], "index": 29, "start": 193366, "end": 196166}, {"text": ["But why worry about that now?"], "index": 30, "start": 199200, "end": 200766}, {"text": ["Aren't you hungry?"], "index": 31, "start": 200766, "end": 201866}, {"text": ["Yes."], "index": 32, "start": 201866, "end": 202900}, {"text": ["[Startled gasp]"], "index": 33, "start": 205666, "end": 207033}, {"text": ["Welcome home, Daddy."], "index": 34, "start": 207033, "end": 208200}, {"text": ["Huh?"], "index": 35, "start": 210500, "end": 211200}, {"text": ["It's nice to see you again, Uncle."], "index": 36, "start": 214100, "end": 216666}, {"text": ["Who are you?! Who said you could sit in my chair?!"], "index": 37, "start": 216666, "end": 218200}, {"text": ["You won't get rid of me that easily!"], "index": 38, "start": 220066, "end": 222933}, {"text": ["What are you talking about, Dad?"], "index": 39, "start": 222933, "end": 225200}, {"text": ["Calm down. That's our cousin, Tadahiro."], "index": 40, "start": 225200, "end": 226200}, {"text": ["Oh! Mm-hmm. You said something about him coming."], "index": 41, "start": 227866, "end": 231033}, {"text": ["How long will you be staying with us, Tadahiro?"], "index": 42, "start": 233366, "end": 234933}, {"text": ["Daddy, we told you that already."], "index": 43, "start": 234933, "end": 237600}, {"text": ["Tadahiro will be staying here while he goes to high school."], "index": 44, "start": 237600, "end": 240033}, {"text": ["Thank you for having me, sir."], "index": 45, "start": 240033, "end": 241633}, {"text": ["Hmph!"], "index": 46, "start": 241633, "end": 242433}, {"text": ["That looks pretty good."], "index": 47, "start": 244800, "end": 245600}, {"text": ["Where's my plate?"], "index": 48, "start": 246833, "end": 248000}, {"text": ["Oops. I forgot..."], "index": 49, "start": 248000, "end": 251233}, {"text": ["Hey. Where are you going?"], "index": 50, "start": 257966, "end": 259700}, {"text": ["It's late."], "index": 51, "start": 259700, "end": 260566}, {"text": ["I'm going to see the mist. Will you come with me?"], "index": 52, "start": 262400, "end": 264266}, {"text": ["Um..."], "index": 53, "start": 266666, "end": 267800}, {"text": ["Sure..."], "index": 54, "start": 269600, "end": 271266}, {"text": ["[Light snoring]"], "index": 55, "start": 303800, "end": 305333}, {"text": ["[Yawn]"], "index": 56, "start": 317766, "end": 319333}, {"text": ["How stupid!"], "index": 57, "start": 321300, "end": 323266}, {"text": ["He probably doesn't even remember that!"], "index": 58, "start": 323266, "end": 325033}, {"text": ["It was five years ago, Yuzu."], "index": 59, "start": 325033, "end": 326466}, {"text": ["[Yawn]"], "index": 60, "start": 327666, "end": 328366}, {"text": ["- Morning. - [Shocked yell]"], "index": 61, "start": 334933, "end": 337100}, {"text": ["Hiro! How long have you been sitting there?!"], "index": 62, "start": 337100, "end": 338766}, {"text": ["Only a minute, but I've been up since dawn."], "index": 63, "start": 340366, "end": 342733}, {"text": ["Oh, really, just a minute?"], "index": 64, "start": 342733, "end": 344100}, {"text": ["It's kind of cold, isn't it?"], "index": 65, "start": 344100, "end": 347033}, {"text": ["I wonder if that's because of the mist or if we're in for a cold snap."], "index": 66, "start": 347033, "end": 349633}, {"text": ["- Yuzu... - Yes, what?"], "index": 67, "start": 349633, "end": 351166}, {"text": ["I was just thinking."], "index": 68, "start": 352166, "end": 353333}, {"text": ["Do you remember that time we climbed the mountain to look at the mist?"], "index": 69, "start": 355100, "end": 357800}, {"text": ["[Startled gasp]"], "index": 70, "start": 357800, "end": 359033}, {"text": ["Um, when was that exactly?"], "index": 71, "start": 359033, "end": 360833}, {"text": ["I didn't really think you'd remember."], "index": 72, "start": 362400, "end": 363566}, {"text": ["It must've been forever ago."], "index": 73, "start": 365133, "end": 367066}, {"text": ["I mean, we haven't seen you in like five years or something."], "index": 74, "start": 367066, "end": 368700}, {"text": ["I sound so dumb."], "index": 75, "start": 369866, "end": 371166}, {"text": ["Shut up, shut up, shut up!"], "index": 76, "start": 371166, "end": 372633}, {"text": ["You know..."], "index": 77, "start": 372633, "end": 373466}, {"text": ["I've been moving around so much, ever since I was little."], "index": 78, "start": 375733, "end": 377366}, {"text": ["My memories are all kind of like pictures from a book."], "index": 79, "start": 379300, "end": 381900}, {"text": ["I don't really remember being there or anything."], "index": 80, "start": 381900, "end": 383400}, {"text": ["One thing I do remember clearly is that morning in the mist."], "index": 81, "start": 386500, "end": 388700}, {"text": ["Wow, you guys look cute!"], "index": 82, "start": 394000, "end": 395400}, {"text": ["You look just like those prince and princess dolls."], "index": 83, "start": 397033, "end": 399000}, {"text": ["Shut up! We do not!"], "index": 84, "start": 399000, "end": 401566}, {"text": ["You do. You always did, even when you were little."], "index": 85, "start": 401566, "end": 405033}, {"text": ["A perfect little pair."], "index": 86, "start": 405033, "end": 406400}, {"text": ["[Embarassed gasp, groan]"], "index": 87, "start": 408066, "end": 409633}, {"text": ["Um, the cherry blossoms are pretty."], "index": 88, "start": 419366, "end": 421000}, {"text": ["Uh-huh."], "index": 89, "start": 421800, "end": 424000}, {"text": ["There are a lot of kids at this school."], "index": 90, "start": 424000, "end": 425300}, {"text": ["Uh-huh."], "index": 91, "start": 426333, "end": 428200}, {"text": ["What homeroom are you in?"], "index": 92, "start": 428200, "end": 430466}, {"text": ["- Four. - Really?! Me too!"], "index": 93, "start": 430466, "end": 432633}, {"text": ["Oh!"], "index": 94, "start": 435833, "end": 437466}, {"text": ["Hey, Yuzu!"], "index": 95, "start": 446400, "end": 448033}, {"text": ["[Embarassed shout]"], "index": 96, "start": 448033, "end": 448700}, {"text": ["Seiko! Chika!"], "index": 97, "start": 450833, "end": 452500}, {"text": ["How long were you standing back there?"], "index": 98, "start": 452500, "end": 454666}, {"text": ["I think I heard something about cherry blossoms?"], "index": 99, "start": 454666, "end": 456333}, {"text": ["It's only the first day of school. You have plenty of time."], "index": 100, "start": 458300, "end": 460100}, {"text": ["No, you don't- I just-"], "index": 101, "start": 460100, "end": 462666}, {"text": ["Kidding, Yuzu."], "index": 102, "start": 462666, "end": 464066}, {"text": ["Hi, I'm Seiko Rikiishi."], "index": 103, "start": 464066, "end": 466200}, {"text": ["- And this is... - Chika Yurikusa."], "index": 104, "start": 466200, "end": 468666}, {"text": ["We've been friends with Yuzu since the third grade."], "index": 105, "start": 468666, "end": 471700}, {"text": ["- Oh. I'm, uh... - We know. You're the Amatsu kid."], "index": 106, "start": 471700, "end": 473833}, {"text": ["Uh..."], "index": 107, "start": 473833, "end": 475233}, {"text": ["Yuzu's told us all about you."], "index": 108, "start": 475233, "end": 477133}, {"text": ["Yeah. We couldn't get her to shut up."], "index": 109, "start": 477133, "end": 478566}, {"text": ["No, it's not- I didn't-"], "index": 110, "start": 478566, "end": 480400}, {"text": ["They're kidding. Don't listen, Hiro!"], "index": 111, "start": 480400, "end": 482933}, {"text": ["Um, I would like to welcome all of you to Kasai High School."], "index": 112, "start": 482933, "end": 486566}, {"text": ["Uh, this school, nestled in the bay of the"], "index": 113, "start": 486566, "end": 489766}, {"text": ["historic Hiroshima, is itself historic."], "index": 114, "start": 489766, "end": 493733}, {"text": ["And you should all consider yourselves, uh, a part of the history."], "index": 115, "start": 493733, "end": 496666}, {"text": ["The history of, uh, academic excellence at Kasai High School."], "index": 116, "start": 498333, "end": 501400}, {"text": ["All of you will be expected to live up to this standard of excellence"], "index": 117, "start": 503200, "end": 506200}, {"text": ["and though it may feel like you are, uh, here forever,"], "index": 118, "start": 506200, "end": 510133}, {"text": ["just remember the days will go by like years and the years will-"], "index": 119, "start": 510133, "end": 512500}, {"text": ["[Billowing boom]"], "index": 120, "start": 512500, "end": 514700}, {"text": ["What the hell?!"], "index": 121, "start": 514700, "end": 515566}, {"text": ["[Menacing growl]"], "index": 122, "start": 524000, "end": 526033}, {"text": ["[Terrified screams]"], "index": 123, "start": 531100, "end": 534533}, {"text": ["Ha!"], "index": 124, "start": 544800, "end": 545766}, {"text": ["[Pained growl]"], "index": 125, "start": 546533, "end": 549600}, {"text": ["Yuzu! He's after Tadahiro!"], "index": 126, "start": 555066, "end": 557700}, {"text": ["Get him out of here! Don't worry about me!"], "index": 127, "start": 557700, "end": 558666}, {"text": ["Okay! Come on!"], "index": 128, "start": 560733, "end": 561600}, {"text": ["[Frantic panting]"], "index": 129, "start": 565133, "end": 567033}, {"text": ["Holy crap!"], "index": 130, "start": 567033, "end": 567833}, {"text": ["[Shocked gasp]"], "index": 131, "start": 573100, "end": 574466}, {"text": ["Hiro!"], "index": 132, "start": 578966, "end": 580266}, {"text": ["I have to protect him!"], "index": 133, "start": 581666, "end": 583200}, {"text": ["I'll fight to the death!"], "index": 134, "start": 583200, "end": 584466}, {"text": ["Hiro, stay back!"], "index": 135, "start": 587066, "end": 588933}, {"text": ["- Huh? - Come on!"], "index": 136, "start": 588933, "end": 590633}, {"text": ["Let's see what you got, you bug-eyed freak!"], "index": 137, "start": 590633, "end": 592133}, {"text": ["Yuzu, what is that thing?!"], "index": 138, "start": 595633, "end": 596933}, {"text": ["Yuzu!"], "index": 139, "start": 600966, "end": 601933}, {"text": ["[Shocked gasp]"], "index": 140, "start": 603633, "end": 604600}, {"text": ["[Battle yell]"], "index": 141, "start": 611400, "end": 613600}, {"text": ["[Tired panting]"], "index": 142, "start": 620400, "end": 623200}, {"text": ["Did you... kill it?"], "index": 143, "start": 623200, "end": 624600}, {"text": ["All right!"], "index": 144, "start": 627533, "end": 629533}, {"text": ["Did you see that?! I got him in one shot!"], "index": 145, "start": 629533, "end": 631333}, {"text": ["That was a little too easy."], "index": 146, "start": 631333, "end": 632733}, {"text": ["[Rattle]"], "index": 147, "start": 633400, "end": 635900}, {"text": ["Don't touch her!"], "index": 148, "start": 638133, "end": 639600}, {"text": ["[Pained grunt]"], "index": 149, "start": 640533, "end": 641766}, {"text": ["Hey!"], "index": 150, "start": 646700, "end": 648333}, {"text": ["White Light Beam! Activate!"], "index": 151, "start": 648333, "end": 650600}, {"text": ["[Magic whoosh]"], "index": 152, "start": 652033, "end": 653900}, {"text": ["That's so cool..."], "index": 153, "start": 657166, "end": 658600}, {"text": ["[Rumbling crack]"], "index": 154, "start": 666566, "end": 668600}, {"text": ["Are you okay?"], "index": 155, "start": 672166, "end": 674100}, {"text": ["Mm-hmm. Thank you for saving my life, Hiro."], "index": 156, "start": 674100, "end": 677366}, {"text": ["Looks like you have to keep saving mine, doesn't it, Yuzu?"], "index": 157, "start": 677366, "end": 679666}]