[{"text": ["Three junior high school girls, Hikaru", "Shidou, Umi Ryuuzaki and Fuu Hououji"], "index": 1, "start": 98360, "end": 104290}, {"text": ["have been summoned by Princess", "Emeraude to become the Magic Knights"], "index": 2, "start": 104290, "end": 109130}, {"text": ["and save an alternate", "world called Cephiro."], "index": 3, "start": 109130, "end": 113000}, {"text": ["Hikaru and her friends finally", "managed to acquire two Rune Gods,"], "index": 4, "start": 113000, "end": 117380}, {"text": ["and continued on their journey in", "search of the last remaining Rune God."], "index": 5, "start": 117380, "end": 122180}, {"text": ["Along the way the girls were", "attacked by Swordmaster Lafarga,"], "index": 6, "start": 122180, "end": 125850}, {"text": ["who was under the", "control of High Priest Zagato."], "index": 7, "start": 125850, "end": 128730}, {"text": ["As they fought, Lafarga", "began to regain his memory."], "index": 8, "start": 128730, "end": 131940}, {"text": ["As captain of the guard, it was his duty", "to protect Princess Emeraude above all."], "index": 9, "start": 131940, "end": 136900}, {"text": ["In the end, the girls", "gained yet another"], "index": 10, "start": 136900, "end": 139831}, {"text": ["powerful ally in the", "crumbling world of Cephiro."], "index": 11, "start": 139855, "end": 143540}, {"text": ["The Truth About Inouva,", "and the Return of Memories"], "index": 12, "start": 144200, "end": 148710}, {"text": ["[Thunder rumbles]"], "index": 13, "start": 151670, "end": 157630}, {"text": ["- [Panting]", "- [Frantic \"puu\"ing]"], "index": 14, "start": 158260, "end": 166390}, {"text": ["[Thunder rumbles] [Exhausted gasp]"], "index": 15, "start": 166933, "end": 170386}, {"text": ["Hey, is something", "the matter, Hikaru?"], "index": 16, "start": 171400, "end": 173520}, {"text": ["Miss Hikaru?"], "index": 17, "start": 173520, "end": 175110}, {"text": ["It doesn't get sunny", "in Cephiro anymore."], "index": 18, "start": 175110, "end": 178110}, {"text": ["When we were first", "summoned here the first"], "index": 19, "start": 178110, "end": 180209}, {"text": ["thing I noticed was", "the beautiful sky."], "index": 20, "start": 180233, "end": 182280}, {"text": ["Yes, I agree with you."], "index": 21, "start": 182280, "end": 183870}, {"text": ["[Alarmed shout]"], "index": 22, "start": 183870, "end": 185910}, {"text": ["Puu puu puu!"], "index": 23, "start": 186620, "end": 188910}, {"text": ["[Startled gasp]"], "index": 24, "start": 189710, "end": 191500}, {"text": ["[Ground rumbles] [Startled yells]"], "index": 25, "start": 191948, "end": 197479}, {"text": ["The ground split open!"], "index": 26, "start": 201470, "end": 203090}, {"text": ["Yeah, it looks like this world", "is really beginning to fall apart."], "index": 27, "start": 203090, "end": 206140}, {"text": ["[Startled gasps]"], "index": 28, "start": 206140, "end": 207770}, {"text": ["Puu puuuuu. [Magic hums]"], "index": 29, "start": 209140, "end": 211390}, {"text": ["Oh!", "Look at the jewel on Mokona's forehead!"], "index": 30, "start": 211390, "end": 213900}, {"text": ["Puu, puu-puu! [Magic hums]"], "index": 31, "start": 214230, "end": 217070}, {"text": ["It's Clef!"], "index": 32, "start": 221990, "end": 223660}, {"text": ["Oh, Clef! How are you?"], "index": 33, "start": 223660, "end": 225830}, {"text": ["We haven't heard", "from you in quite a while,"], "index": 34, "start": 225830, "end": 227451}, {"text": ["and we've been worried", "about you, Mister Clef."], "index": 35, "start": 227475, "end": 229290}, {"text": ["Are you alright?"], "index": 36, "start": 229290, "end": 230830}, {"text": ["Hey Clef?"], "index": 37, "start": 232250, "end": 233920}, {"text": ["What's the matter, Mister Clef?"], "index": 38, "start": 233920, "end": 235880}, {"text": ["Young girls from another world,"], "index": 39, "start": 236880, "end": 238760}, {"text": ["I believe that this will be the", "last time I communicate with you."], "index": 40, "start": 239510, "end": 243340}, {"text": ["Oh, Clef!"], "index": 41, "start": 243840, "end": 245890}, {"text": ["I can no longer suppress Zagato's", "magic, which has turned me into stone."], "index": 42, "start": 245890, "end": 250230}, {"text": ["Clef, you can't give up!"], "index": 43, "start": 250850, "end": 252810}, {"text": ["The collapse of", "Cephiro is nearing."], "index": 44, "start": 253770, "end": 256230}, {"text": ["Hurry, before it is too late."], "index": 45, "start": 256230, "end": 258690}, {"text": ["Lord of the Sea, Selece."], "index": 46, "start": 258690, "end": 261280}, {"text": ["Lord of the Sky, Windam."], "index": 47, "start": 261280, "end": 263570}, {"text": ["The three of you have", "triumphed over many hardships,"], "index": 48, "start": 264910, "end": 267700}, {"text": ["and successfully", "revived two Rune Gods."], "index": 49, "start": 267700, "end": 270950}, {"text": ["Only the very last", "Rune God remains."], "index": 50, "start": 270950, "end": 273540}, {"text": ["The very last Rune God..."], "index": 51, "start": 273540, "end": 275920}, {"text": ["Hurry."], "index": 52, "start": 276330, "end": 277840}, {"text": ["I'm afraid that before you", "are able to grant Princess"], "index": 53, "start": 278590, "end": 281559}, {"text": ["Emeraude's wish, you", "will collapse with Cephiro,"], "index": 54, "start": 281583, "end": 284380}, {"text": ["and be eradicated", "from this world."], "index": 55, "start": 284380, "end": 286510}, {"text": ["Collapse?"], "index": 56, "start": 286510, "end": 287800}, {"text": ["Eradicated?"], "index": 57, "start": 287800, "end": 289470}, {"text": ["Yes. The three of you will never", "be able to return to your world."], "index": 58, "start": 289470, "end": 293980}, {"text": ["[Startled gasp]"], "index": 59, "start": 293980, "end": 294980}, {"text": ["Please hurry, young", "girls from another world."], "index": 60, "start": 294980, "end": 298440}, {"text": ["Continue to follow Mokona's", "guidance, and revive the final Rune God."], "index": 61, "start": 299610, "end": 303490}, {"text": ["Then, with three Rune Gods,", "you will become the Magic Knights."], "index": 62, "start": 303860, "end": 308490}, {"text": ["- But Clef - Don't go!"], "index": 63, "start": 308490, "end": 310950}, {"text": ["I have one more thing to say,", "young girls from another world."], "index": 64, "start": 311330, "end": 314790}, {"text": ["Your true enemy is..."], "index": 65, "start": 314790, "end": 317170}, {"text": ["Oh, Clef."], "index": 66, "start": 317170, "end": 318790}, {"text": ["Puu puu."], "index": 67, "start": 318790, "end": 320300}, {"text": ["If the three of us do our best, we", "might still be able to save this world."], "index": 68, "start": 320300, "end": 324760}, {"text": ["Cephiro."], "index": 69, "start": 324760, "end": 326180}, {"text": ["Alright then. Let's get going.", "We don't have much time left."], "index": 70, "start": 329050, "end": 332600}, {"text": ["Mmm."], "index": 71, "start": 332600, "end": 334020}, {"text": ["[Heartbeat thumping]"], "index": 72, "start": 335963, "end": 340320}, {"text": ["[Soft cries] Zagato,", "please stop this."], "index": 73, "start": 340320, "end": 344740}, {"text": ["At this rate, the damage", "cannot be undone."], "index": 74, "start": 345360, "end": 349870}, {"text": ["[Cries softly] Zagato..."], "index": 75, "start": 349870, "end": 353450}, {"text": ["Lord Zagato."], "index": 76, "start": 374850, "end": 376680}, {"text": ["My lord, what is the condition", "of Princess Emeraude?"], "index": 77, "start": 380150, "end": 383440}, {"text": ["She's the same. She has not", "wavered since the battle first began."], "index": 78, "start": 383440, "end": 388110}, {"text": ["Her tears have not", "stopped for a single moment."], "index": 79, "start": 388110, "end": 391070}, {"text": ["Alcyone, Ascot, Caldina and Lafarga. None", "were able to defeat the Magic Knights."], "index": 80, "start": 392370, "end": 398540}, {"text": ["And of course, neither could I."], "index": 81, "start": 399080, "end": 401880}, {"text": ["[Wind howls]"], "index": 82, "start": 401880, "end": 406590}, {"text": ["This can't be! Impossible!"], "index": 83, "start": 406590, "end": 409720}, {"text": ["[Magic hums]"], "index": 84, "start": 413296, "end": 416054}, {"text": ["The Rune God, awake!"], "index": 85, "start": 420770, "end": 423520}, {"text": ["This power is too..."], "index": 86, "start": 423770, "end": 425730}, {"text": ["[Pained scream]"], "index": 87, "start": 425730, "end": 428490}, {"text": ["My lord.", "I humbly request that you grant me"], "index": 88, "start": 434410, "end": 436858}, {"text": ["permission to go after", "those Magic Knights,"], "index": 89, "start": 436882, "end": 439330}, {"text": ["one last time."], "index": 90, "start": 439330, "end": 441120}, {"text": ["Those three girls from another world", "were able to defeat me in this form."], "index": 91, "start": 441420, "end": 445670}, {"text": ["But if I were to revert to my original", "form, I'd be able to use all of my powers."], "index": 92, "start": 445670, "end": 451050}, {"text": ["Lord Zagato, I ask that you please", "consider what I'm saying to you."], "index": 93, "start": 451630, "end": 455470}, {"text": ["Lord Zagato!"], "index": 94, "start": 456220, "end": 457890}, {"text": ["I know the reason that you", "have kept me at your side, my lord!"], "index": 95, "start": 457890, "end": 460890}, {"text": ["It's because I was a creature the", "Princess presented to you as a gift."], "index": 96, "start": 460890, "end": 464810}, {"text": ["My last request is that you now", "return me to my original shape."], "index": 97, "start": 466360, "end": 469690}, {"text": ["Change me back to what I was before", "any of this ever happened, my lord."], "index": 98, "start": 469690, "end": 473780}, {"text": ["Inouva, you are not ordinary.", "You are a"], "index": 99, "start": 474320, "end": 476748}, {"text": ["creature with the", "highest magical powers."], "index": 100, "start": 476772, "end": 479200}, {"text": ["And you realize that", "that is the only reason I"], "index": 101, "start": 480410, "end": 483318}, {"text": ["was able to turn you into", "a human as you wished."], "index": 102, "start": 483342, "end": 486250}, {"text": ["Yes, it is true I'd always", "wished to take this form."], "index": 103, "start": 486250, "end": 489460}, {"text": ["I know that it is unforgivably selfish", "of me to ask that you now change me back."], "index": 104, "start": 489460, "end": 494180}, {"text": ["It was I who informed", "you that by taking"], "index": 105, "start": 494180, "end": 496458}, {"text": ["this shape, I'd be", "able to wield a sword,"], "index": 106, "start": 496482, "end": 498760}, {"text": ["and take command over those that", "we gathered to defeat the Magic Knights,"], "index": 107, "start": 498760, "end": 502310}, {"text": ["when I first asked to be", "changed into human form, my lord."], "index": 108, "start": 502310, "end": 505860}, {"text": ["However..."], "index": 109, "start": 506150, "end": 507690}, {"text": ["However, now that", "the Magic Knights have"], "index": 110, "start": 509650, "end": 511931}, {"text": ["somehow managed to", "get as far as they have,"], "index": 111, "start": 511955, "end": 514530}, {"text": ["now that two Rune Gods are revived,", "I must use every ounce of power I can."], "index": 112, "start": 514570, "end": 519290}, {"text": ["Inouva."], "index": 113, "start": 519330, "end": 520910}, {"text": ["My lord, please grant", "me one more chance to"], "index": 114, "start": 520910, "end": 523068}, {"text": ["repay you for always", "keeping me at your side,"], "index": 115, "start": 523092, "end": 525250}, {"text": ["even if only because I was a", "gift from Princess Emeraude."], "index": 116, "start": 525250, "end": 528670}, {"text": ["Once you revert to", "your previous form, you"], "index": 117, "start": 529050, "end": 531457}, {"text": ["will never again be able", "to take a human shape."], "index": 118, "start": 531481, "end": 534300}, {"text": ["Yes, I understand, my lord."], "index": 119, "start": 534840, "end": 537510}, {"text": ["Inouva, why do you remain", "so completely devoted to me?"], "index": 120, "start": 537510, "end": 541350}, {"text": ["Because I have seen you beside", "the princess all of this time, my lord."], "index": 121, "start": 541390, "end": 545480}, {"text": ["And I have seen you", "reveal your emotions as well."], "index": 122, "start": 545480, "end": 549360}, {"text": ["Cephiro is a land of the will.", "The heart will always triumph."], "index": 123, "start": 549360, "end": 554530}, {"text": ["There's no chance your", "wish will not come true."], "index": 124, "start": 554530, "end": 557990}, {"text": ["You say that even", "though it is an evil wish that"], "index": 125, "start": 559410, "end": 562106}, {"text": ["will destroy everything", "of value in Cephiro."], "index": 126, "start": 562130, "end": 564710}, {"text": ["No."], "index": 127, "start": 564710, "end": 566170}, {"text": ["Let them call you evil, Lord Zagato.", "It does not matter to me."], "index": 128, "start": 566170, "end": 569790}, {"text": ["The only thing of", "importance is to make"], "index": 129, "start": 569790, "end": 571716}, {"text": ["sure that you are", "able to reach your goal."], "index": 130, "start": 571740, "end": 573920}, {"text": ["Alright, Inouva."], "index": 131, "start": 573920, "end": 576180}, {"text": ["[Relieved sigh]"], "index": 132, "start": 576380, "end": 578050}, {"text": ["[Magic hums]"], "index": 133, "start": 585770, "end": 589980}, {"text": ["[Pained groans]"], "index": 134, "start": 589980, "end": 596860}, {"text": ["[Pained screams]"], "index": 135, "start": 597320, "end": 602490}, {"text": ["[Low growl]"], "index": 136, "start": 608733, "end": 613750}, {"text": ["Inouva..."], "index": 137, "start": 614590, "end": 616260}, {"text": ["[Howls]"], "index": 138, "start": 620340, "end": 623140}, {"text": ["[Magic ripples]"], "index": 139, "start": 626600, "end": 629980}, {"text": ["[Heavy panting]"], "index": 140, "start": 639950, "end": 646080}, {"text": ["[Startled gasps]"], "index": 141, "start": 646080, "end": 647580}, {"text": ["- Let's go!", "- Mmm!"], "index": 142, "start": 648120, "end": 649830}, {"text": ["[Heavy panting]"], "index": 143, "start": 649830, "end": 653750}, {"text": ["[Thunder crashes]"], "index": 144, "start": 654000, "end": 656010}, {"text": ["Puu-puu-puu! [Startled gasp]"], "index": 145, "start": 656010, "end": 658840}, {"text": ["- What's that?", "- Puu puu?"], "index": 146, "start": 660220, "end": 663140}, {"text": ["[Thunder crashes,", "Startled shouts]"], "index": 147, "start": 664850, "end": 667520}, {"text": ["[Thunder crashes] [Flames crackle]"], "index": 148, "start": 667683, "end": 670575}, {"text": ["[Strained grunts]"], "index": 149, "start": 670600, "end": 672400}, {"text": ["[Surprised gasps]"], "index": 150, "start": 672400, "end": 674440}, {"text": ["[Thunder crashes]"], "index": 151, "start": 677360, "end": 680070}, {"text": ["What in the world is that!?"], "index": 152, "start": 682450, "end": 684080}, {"text": ["[Low growl]"], "index": 153, "start": 684080, "end": 687540}, {"text": ["Is it a beast!?"], "index": 154, "start": 691620, "end": 693580}, {"text": ["[Menacing howl]"], "index": 155, "start": 693630, "end": 696960}, {"text": ["[Magic chimes]"], "index": 156, "start": 698339, "end": 703220}, {"text": ["[Startled shouts]"], "index": 157, "start": 704930, "end": 706930}, {"text": ["[Worried gasp]"], "index": 158, "start": 727239, "end": 728715}, {"text": ["[Low growls]"], "index": 159, "start": 728740, "end": 732620}, {"text": ["That beast!", "That beast is trying to kill us!"], "index": 160, "start": 743510, "end": 746800}, {"text": ["Little girls from another world!"], "index": 161, "start": 749640, "end": 752060}, {"text": ["Huh? Hey! Did you hear that?"], "index": 162, "start": 752230, "end": 755150}, {"text": ["A voice... in my head."], "index": 163, "start": 755150, "end": 757310}, {"text": ["It must be the voice", "of that white beast."], "index": 164, "start": 757310, "end": 760400}, {"text": ["Girls from another world. I'm afraid", "that I cannot let you go any further."], "index": 165, "start": 760400, "end": 765780}, {"text": ["Who are you, and", "what do you want!?"], "index": 166, "start": 765780, "end": 768240}, {"text": ["[Evil laugh] [Magic crackles]"], "index": 167, "start": 768240, "end": 773870}, {"text": ["[Startled gasps]"], "index": 168, "start": 774250, "end": 776080}, {"text": ["[Whooshing impact]"], "index": 169, "start": 776497, "end": 779184}, {"text": ["[Frightened screams]"], "index": 170, "start": 780880, "end": 782970}, {"text": ["[Thunder crashes]"], "index": 171, "start": 783010, "end": 787010}, {"text": ["Man, the skies of Cephiro", "used to be so beautiful until now."], "index": 172, "start": 787470, "end": 791810}, {"text": ["Hikaru... Umi..."], "index": 173, "start": 791810, "end": 793930}, {"text": ["...and Fuu..."], "index": 174, "start": 796230, "end": 797690}, {"text": ["I sure hope they're safe as", "they continue on their journey."], "index": 175, "start": 798480, "end": 801360}, {"text": ["Please do everything", "you can to protect those"], "index": 176, "start": 802650, "end": 804893}, {"text": ["three girls you summoned", "from another world."], "index": 177, "start": 804917, "end": 807160}, {"text": ["Please, Princess Emeraude."], "index": 178, "start": 807660, "end": 809580}, {"text": ["That item is something I", "gave to this young man as a gift."], "index": 179, "start": 813370, "end": 817370}, {"text": ["He did not steal it."], "index": 180, "start": 817370, "end": 819040}, {"text": ["Ferio."], "index": 181, "start": 821460, "end": 823050}, {"text": ["Ferio..."], "index": 182, "start": 826630, "end": 828430}, {"text": ["Wait a second! What the...!?"], "index": 183, "start": 829260, "end": 831510}, {"text": ["That day, when I was", "wandering around the castle."], "index": 184, "start": 832140, "end": 835230}, {"text": ["Instead of punishing me,", "she let me keep this orb."], "index": 185, "start": 835810, "end": 839690}, {"text": ["Ferio..."], "index": 186, "start": 839690, "end": 841440}, {"text": ["I never thought about it, but how the", "heck did Princess Emeraude know my name?"], "index": 187, "start": 842320, "end": 845820}, {"text": ["We'd never me before."], "index": 188, "start": 845820, "end": 847660}, {"text": ["Ferio."], "index": 189, "start": 848280, "end": 849620}, {"text": ["[Strained sigh]"], "index": 190, "start": 850200, "end": 851410}, {"text": ["A child. But who is that child?"], "index": 191, "start": 851410, "end": 854620}, {"text": ["Why is she calling my name?"], "index": 192, "start": 855620, "end": 857750}, {"text": ["[Thunder crashes]"], "index": 193, "start": 858370, "end": 860210}, {"text": ["[Magic whooshes]"], "index": 194, "start": 860392, "end": 862658}, {"text": ["[Magic crackles] [Evil laugh]"], "index": 195, "start": 863420, "end": 866050}, {"text": ["It is I, Magic Knights."], "index": 196, "start": 866220, "end": 868470}, {"text": ["[Strained groan]"], "index": 197, "start": 868470, "end": 871430}, {"text": ["So, who are you!?"], "index": 198, "start": 871680, "end": 873350}, {"text": ["[Evil laugh]"], "index": 199, "start": 873850, "end": 875890}, {"text": ["You still don't understand."], "index": 200, "start": 876230, "end": 878350}, {"text": ["The last time we met", "was at the Sky Shrine."], "index": 201, "start": 878940, "end": 882060}, {"text": ["I'm sure I've heard that voice."], "index": 202, "start": 882520, "end": 884610}, {"text": ["It said the Sky Shrine..."], "index": 203, "start": 885150, "end": 887070}, {"text": ["Then you must be", "the one who tried to..."], "index": 204, "start": 887070, "end": 889490}, {"text": ["My name is Inouva."], "index": 205, "start": 889490, "end": 891490}, {"text": ["I stand here with an order from the High", "Priest Zagato to kill the Magic Knights."], "index": 206, "start": 891490, "end": 897120}, {"text": ["Now you see me in my", "true form, Magic Knights."], "index": 207, "start": 897120, "end": 901380}, {"text": ["[Startled gasps]"], "index": 208, "start": 901380, "end": 902750}, {"text": ["And you see, now that I've", "reverted to this form, you cannot win!"], "index": 209, "start": 902750, "end": 908380}, {"text": ["[Frightened screams]"], "index": 210, "start": 908800, "end": 912470}, {"text": ["Ferio!"], "index": 211, "start": 912470, "end": 914640}, {"text": ["I've always...", "I've always been alone all my life,"], "index": 212, "start": 915510, "end": 918310}, {"text": ["and I've never known my parents", "or had any brothers or sisters."], "index": 213, "start": 918310, "end": 921900}, {"text": ["[Gasp] Wait a minute!"], "index": 214, "start": 921900, "end": 924150}, {"text": ["Sister!"], "index": 215, "start": 924730, "end": 927190}, {"text": ["Sister!"], "index": 216, "start": 927940, "end": 929780}, {"text": ["Ferio."], "index": 217, "start": 931490, "end": 932820}, {"text": ["Well, we shall never meet again."], "index": 218, "start": 933740, "end": 936950}, {"text": ["My only dear,", "sweet little brother."], "index": 219, "start": 937580, "end": 940920}, {"text": ["[Thunder crashes] No way!"], "index": 220, "start": 941620, "end": 943830}, {"text": ["[Startled gasp] I am Princess", "Emeraude's little brother!?"], "index": 221, "start": 944670, "end": 949050}, {"text": ["Elder sister, I have one small", "request before we say goodbye."], "index": 222, "start": 956680, "end": 960890}, {"text": ["A request?"], "index": 223, "start": 961310, "end": 962850}, {"text": ["Yes, I want you to", "erase all of my memories."], "index": 224, "start": 963230, "end": 966610}, {"text": ["As the Pillar of Cephiro, you", "will have to support this world."], "index": 225, "start": 967520, "end": 971150}, {"text": ["I want you to have fewer", "problems to worry about."], "index": 226, "start": 971150, "end": 974070}, {"text": ["If I can never see you", "again, I want to live alone and"], "index": 227, "start": 975410, "end": 978173}, {"text": ["be sure that I'll never", "bother you as long as I live."], "index": 228, "start": 978197, "end": 980960}, {"text": ["So please, you should try to forget", "that you ever had a brother, too."], "index": 229, "start": 981540, "end": 985960}, {"text": ["I remember!"], "index": 230, "start": 987460, "end": 989090}, {"text": ["I received this orb from", "her when I left the castle."], "index": 231, "start": 989590, "end": 992840}, {"text": ["Even if I erase your", "memory, Ferio, I do"], "index": 232, "start": 994590, "end": 997155}, {"text": ["not think I will ever", "be able to forget you."], "index": 233, "start": 997179, "end": 1000140}, {"text": ["I want you to take", "these orbs with you, so"], "index": 234, "start": 1001100, "end": 1003883}, {"text": ["that I can hear your", "voice from far away,"], "index": 235, "start": 1003907, "end": 1006690}, {"text": ["from wherever you may be."], "index": 236, "start": 1007060, "end": 1009020}, {"text": ["That way I will never forget the", "voice of my dear, sweet only brother."], "index": 237, "start": 1009020, "end": 1014110}, {"text": ["I see."], "index": 238, "start": 1014780, "end": 1016160}, {"text": ["So that's the reason I've", "always been so worried about you."], "index": 239, "start": 1016160, "end": 1019120}, {"text": ["The reason I couldn't", "just stand by when I first"], "index": 240, "start": 1019950, "end": 1022233}, {"text": ["found out that Cephiro", "was starting to crumble,"], "index": 241, "start": 1022257, "end": 1024540}, {"text": ["and I couldn't bear the", "thought of you in danger."], "index": 242, "start": 1024540, "end": 1027210}, {"text": ["It is because you were", "my one and only sister."], "index": 243, "start": 1027210, "end": 1030460}, {"text": ["[Thunder crashes]"], "index": 244, "start": 1030460, "end": 1032510}, {"text": ["- [Pained groan]", "- Hey, Fuu!"], "index": 245, "start": 1032510, "end": 1034800}, {"text": ["Water...!"], "index": 246, "start": 1035430, "end": 1037390}, {"text": ["[roars]"], "index": 247, "start": 1038510, "end": 1041060}, {"text": ["...Dragon!"], "index": 248, "start": 1042220, "end": 1044180}, {"text": ["[Magic crackles]"], "index": 249, "start": 1046810, "end": 1049440}, {"text": ["Don't tell me that", "magic doesn't work!"], "index": 250, "start": 1049440, "end": 1052360}, {"text": ["Ferio, I see that your", "memory is returning to you."], "index": 251, "start": 1054030, "end": 1057990}, {"text": ["Sister! Sister, is that you!?"], "index": 252, "start": 1058280, "end": 1060830}, {"text": ["Are you willing to call", "me your sister once again?"], "index": 253, "start": 1062540, "end": 1066000}, {"text": ["The reason that all", "of the memories in you"], "index": 254, "start": 1066330, "end": 1068758}, {"text": ["that I once erased", "have begun to return,"], "index": 255, "start": 1068782, "end": 1071210}, {"text": ["is because my", "powers are weakening,"], "index": 256, "start": 1071210, "end": 1073800}, {"text": ["and the seal on your memories", "has finally been released."], "index": 257, "start": 1073800, "end": 1077680}, {"text": ["Please, tell me!", "Tell me how I can help"], "index": 258, "start": 1078050, "end": 1080083}, {"text": ["you to get out of", "this situation, Sister!"], "index": 259, "start": 1080107, "end": 1082140}, {"text": ["Only those from", "another world can do this,"], "index": 260, "start": 1083810, "end": 1087310}, {"text": ["and at this moment the girls", "are facing life-threatening danger."], "index": 261, "start": 1088060, "end": 1093610}, {"text": ["Ferio, please. I need you to", "lend me all of your strength."], "index": 262, "start": 1094900, "end": 1099200}, {"text": ["[Thunder crashes]"], "index": 263, "start": 1101530, "end": 1103700}, {"text": ["Please save the Magic Knights."], "index": 264, "start": 1103870, "end": 1106710}, {"text": ["[Exhausted panting]"], "index": 265, "start": 1108120, "end": 1109580}, {"text": ["Umi! Are you and Fuu doing okay?"], "index": 266, "start": 1109580, "end": 1112250}, {"text": ["You gotta hang in there, Fuu!"], "index": 267, "start": 1112250, "end": 1114250}, {"text": ["Don't worry. I'm doing alright."], "index": 268, "start": 1115550, "end": 1118010}, {"text": ["At this point, you must do something", "about the enemy we're facing."], "index": 269, "start": 1118550, "end": 1122970}, {"text": ["Get ready! I'm sure he'll try to", "finish us off with his next attack!"], "index": 270, "start": 1123930, "end": 1127850}, {"text": ["[Evil laugh]"], "index": 271, "start": 1129440, "end": 1131900}, {"text": ["I congratulate you heartily for", "surviving as long as you have."], "index": 272, "start": 1131900, "end": 1135400}, {"text": ["But unfortunately,", "this is as far as you go."], "index": 273, "start": 1136190, "end": 1139280}, {"text": ["Hikaru, Umi, Fuu! If you guys can hear", "me, you've gotta let me know right now!"], "index": 274, "start": 1140110, "end": 1143660}, {"text": ["[Surprised gasp] Oh! Ferio!"], "index": 275, "start": 1143660, "end": 1146200}, {"text": ["Ferio, I'm so", "glad you're alright!"], "index": 276, "start": 1147160, "end": 1149710}, {"text": ["Don't worry about me! I want you", "guys to listen to me extremely closely!"], "index": 277, "start": 1149710, "end": 1153630}, {"text": ["The creature you are fighting", "called Inouva has one weakness."], "index": 278, "start": 1154130, "end": 1157260}, {"text": ["The gem on his forehead."], "index": 279, "start": 1157260, "end": 1159260}, {"text": ["You must attack that gem!"], "index": 280, "start": 1159260, "end": 1161430}, {"text": ["No use! Our swords and magic", "haven't had any effect on it so far!"], "index": 281, "start": 1161430, "end": 1165560}, {"text": ["Umi, I want you to", "take care of Fuu, okay?"], "index": 282, "start": 1166180, "end": 1169230}, {"text": ["You can't fight", "it alone, Hikaru!"], "index": 283, "start": 1169730, "end": 1171690}, {"text": ["Don't be reckless!"], "index": 284, "start": 1171690, "end": 1173610}, {"text": ["We promised everybody", "that no matter what happens,"], "index": 285, "start": 1173610, "end": 1176610}, {"text": ["we will become the Magic", "Knights, and we will save Cephiro."], "index": 286, "start": 1176610, "end": 1180530}, {"text": ["So don't ever give up."], "index": 287, "start": 1181610, "end": 1183160}, {"text": ["Right Umi? Right Fuu?"], "index": 288, "start": 1183160, "end": 1184910}, {"text": ["Die, Magic Knights!"], "index": 289, "start": 1185370, "end": 1188040}, {"text": ["[Battle shout]"], "index": 290, "start": 1188040, "end": 1191870}, {"text": ["[Energy crackles]"], "index": 291, "start": 1191870, "end": 1194380}, {"text": ["[Pained grunt] [Gem shatters]"], "index": 292, "start": 1194380, "end": 1196210}, {"text": ["[Pained howl]"], "index": 293, "start": 1196210, "end": 1198760}, {"text": ["[Sword squelches]"], "index": 294, "start": 1200056, "end": 1202494}, {"text": ["My lord, Zagato."], "index": 295, "start": 1206140, "end": 1208680}, {"text": ["Inouva."], "index": 296, "start": 1209220, "end": 1211190}, {"text": ["Inouva."], "index": 297, "start": 1211190, "end": 1212520}, {"text": ["[Howls]"], "index": 298, "start": 1212520, "end": 1216150}, {"text": ["[Energy crackles]"], "index": 299, "start": 1216150, "end": 1220490}, {"text": ["Welcome back.", "I was worried about'cha."], "index": 300, "start": 1228990, "end": 1231660}, {"text": ["Hey Ferio!"], "index": 301, "start": 1231660, "end": 1232920}, {"text": ["Hey, there's Umi! And Fuu, too!"], "index": 302, "start": 1232920, "end": 1235630}, {"text": ["Yeah, we're alright."], "index": 303, "start": 1236040, "end": 1238090}, {"text": ["And we were able to defeat", "that beast called Inouva."], "index": 304, "start": 1238590, "end": 1241800}, {"text": ["It was all thanks to you, Ferio."], "index": 305, "start": 1242760, "end": 1245550}, {"text": ["Well, no.", "To tell you the truth it was Princess"], "index": 306, "start": 1248930, "end": 1251477}, {"text": ["Emeraude who told", "me about his weakness."], "index": 307, "start": 1251501, "end": 1253770}, {"text": ["Princess Emeraude?"], "index": 308, "start": 1253770, "end": 1255600}, {"text": ["Isn't this...", "isn't this your orb, Ferio?"], "index": 309, "start": 1255810, "end": 1258730}, {"text": ["Princess Emeraude's powers", "have become severely weakened."], "index": 310, "start": 1261320, "end": 1264360}, {"text": ["The only way she'll be able to communicate", "with you is through this magic orb."], "index": 311, "start": 1265030, "end": 1269330}, {"text": ["That's why it's important that you", "hang onto this thing from now on."], "index": 312, "start": 1270160, "end": 1274410}, {"text": ["But Ferio... is something wrong?"], "index": 313, "start": 1274410, "end": 1276830}, {"text": ["Puu puu?"], "index": 314, "start": 1281210, "end": 1283170}, {"text": ["The only ones who can", "save our Princess Emeraude"], "index": 315, "start": 1284470, "end": 1287077}, {"text": ["are the Magic Knights", "from another world."], "index": 316, "start": 1287101, "end": 1289430}, {"text": ["Hikaru, Umi and Fuu...", "please save the princess."], "index": 317, "start": 1289430, "end": 1293230}, {"text": ["Save the princess,", "and save Cephiro."], "index": 318, "start": 1294730, "end": 1296980}, {"text": ["Ferio..."], "index": 319, "start": 1297600, "end": 1299400}, {"text": ["My lord Zagato."], "index": 320, "start": 1308740, "end": 1310120}, {"text": ["I've returned with a plan to defeat", "the Magic Knights once and for all."], "index": 321, "start": 1310120, "end": 1313830}, {"text": ["My lord, please grant me this", "one last chance to defeat them."], "index": 322, "start": 1314160, "end": 1317710}, {"text": ["[Surprised gasp]"], "index": 323, "start": 1317710, "end": 1319500}, {"text": ["Wait just a moment, my lord!"], "index": 324, "start": 1323920, "end": 1326470}, {"text": ["Please! Lord Zagato!"], "index": 325, "start": 1326470, "end": 1329430}, {"text": ["Lord Zagato!"], "index": 326, "start": 1332720, "end": 1335100}, {"text": ["Who is it today?"], "index": 327, "start": 1461890, "end": 1463900}, {"text": ["Today, it's Hikaru!"], "index": 328, "start": 1467520, "end": 1469610}, {"text": ["Hey everybody! Did you guess right?", "I'll see you later!"], "index": 329, "start": 1470280, "end": 1475700}]