[{"text": ["Please save us,", "Legendary Magic Knights."], "index": 1, "start": 97360, "end": 100200}, {"text": ["Three junior high school girls, Hikaru", "Shidou, Umi Ryuuzaki and Fuu Hououji"], "index": 2, "start": 101120, "end": 106330}, {"text": ["have been summoned by Princess", "Emeraude to become the Magic Knights"], "index": 3, "start": 106330, "end": 110790}, {"text": ["and save an alternate", "world called Cephiro."], "index": 4, "start": 110790, "end": 115220}, {"text": ["Inouva has sworn undying", "allegiance to High Priest Zagato,"], "index": 5, "start": 116800, "end": 121470}, {"text": ["who imprisoned", "Princess Emeraude."], "index": 6, "start": 121470, "end": 123600}, {"text": ["The three girls barely survived", "Inouva's vicious attacks upon them,"], "index": 7, "start": 123600, "end": 127600}, {"text": ["and Fuu, with the help of her friends,", "was able to acquire the Rune God of Wind,"], "index": 8, "start": 127890, "end": 133270}, {"text": ["called Windam."], "index": 9, "start": 133270, "end": 135150}, {"text": ["And now the trio continue", "their treacherous journey,"], "index": 10, "start": 135150, "end": 137990}, {"text": ["in search of the", "remaining Rune God."], "index": 11, "start": 137990, "end": 140740}, {"text": ["Because this world is", "Cephiro, the land of the will."], "index": 12, "start": 141030, "end": 145120}, {"text": ["A Powerful Foe!", "Lafarga the Swordmaster"], "index": 13, "start": 151920, "end": 156510}, {"text": ["[Crying softly]"], "index": 14, "start": 159180, "end": 163300}, {"text": ["Hurry. Please come quickly."], "index": 15, "start": 170900, "end": 174320}, {"text": ["Please hurry,", "Legendary Magic Knights."], "index": 16, "start": 178070, "end": 181410}, {"text": ["Please hurry", "before it's too late."], "index": 17, "start": 183320, "end": 185370}, {"text": ["[Cries softly]"], "index": 18, "start": 185370, "end": 190170}, {"text": ["Are you feeling any pain?"], "index": 19, "start": 193460, "end": 195500}, {"text": ["[Surprised gasp]"], "index": 20, "start": 195500, "end": 197050}, {"text": ["Won't you please stop?", "Please stop this, Zagato."], "index": 21, "start": 202510, "end": 207770}, {"text": ["If you continue, our", "world will finally fall to ruins."], "index": 22, "start": 208390, "end": 213060}, {"text": ["I'm afraid that my", "heart is unchanged."], "index": 23, "start": 215730, "end": 218690}, {"text": ["Even if all of Cephiro", "crumbles to nothing."], "index": 24, "start": 219650, "end": 222393}, {"text": ["Even if everyone in", "this world were to die."], "index": 25, "start": 222417, "end": 225160}, {"text": ["My heart will not waver."], "index": 26, "start": 225160, "end": 227990}, {"text": ["Princess Emeraude."], "index": 27, "start": 234460, "end": 236040}, {"text": ["[Startled gasp] Zagato."], "index": 28, "start": 236040, "end": 238670}, {"text": ["Sea God Selece, Wind God Windam."], "index": 29, "start": 248310, "end": 251850}, {"text": ["Two Rune Gods have", "been awakened from their"], "index": 30, "start": 251850, "end": 254276}, {"text": ["slumber by those three", "girls from another world."], "index": 31, "start": 254300, "end": 257190}, {"text": ["Only one remains."], "index": 32, "start": 257190, "end": 258820}, {"text": ["The scarlet Rune God that lies in", "the Fire Shrine, has not been revived."], "index": 33, "start": 258820, "end": 263280}, {"text": ["[Startled gasp] Oh, it's you!"], "index": 34, "start": 267620, "end": 269490}, {"text": ["Lafarga!"], "index": 35, "start": 269490, "end": 270910}, {"text": ["That's right.", "Lafarga was the Captain of"], "index": 36, "start": 271370, "end": 273777}, {"text": ["the guards that", "protected you in the castle."], "index": 37, "start": 273801, "end": 276580}, {"text": ["Of course, when you were", "the Pillar that supported Cephiro,"], "index": 38, "start": 277500, "end": 281090}, {"text": ["there was never much of anything", "to protect you or the castle from."], "index": 39, "start": 281090, "end": 285260}, {"text": ["Lafarga and the rest of", "the guards were merely"], "index": 40, "start": 286470, "end": 289125}, {"text": ["employed to combat the", "occasional monster or two."], "index": 41, "start": 289149, "end": 292100}, {"text": ["And of course Lafarga was known as", "the strongest swordsman here in Cephiro."], "index": 42, "start": 292850, "end": 297360}, {"text": ["Do you think those", "girls you summoned from"], "index": 43, "start": 297520, "end": 299488}, {"text": ["another world to", "become the Magic Knights"], "index": 44, "start": 299512, "end": 301480}, {"text": ["would be able to stand", "a chance against him?"], "index": 45, "start": 301480, "end": 304280}, {"text": ["No! Please, Lafarga!", "You mustn't!"], "index": 46, "start": 304280, "end": 307280}, {"text": ["Your cries are useless."], "index": 47, "start": 307280, "end": 309370}, {"text": ["[Startled gasp]"], "index": 48, "start": 309370, "end": 310830}, {"text": ["I have cast a spell on", "Lafarga that controls his heart."], "index": 49, "start": 310830, "end": 314910}, {"text": ["How?", "How can you do such a cruel thing?"], "index": 50, "start": 318080, "end": 320960}, {"text": ["Please, Lafarga!", "You must wake up right now!"], "index": 51, "start": 321300, "end": 323880}, {"text": ["Lafarga!"], "index": 52, "start": 323880, "end": 325930}, {"text": ["Go now, Lafarga.", "And when you return, bring with you"], "index": 53, "start": 328220, "end": 331470}, {"text": ["the three corpses of the", "Legendary Magic Knights."], "index": 54, "start": 331494, "end": 334680}, {"text": ["You must not do it, Lafarga!"], "index": 55, "start": 337980, "end": 340360}, {"text": ["Lafarga!"], "index": 56, "start": 340650, "end": 342860}, {"text": ["[Singing happily in \"puu\"]"], "index": 57, "start": 349530, "end": 354700}, {"text": ["Are we going the", "right way, Mokona?"], "index": 58, "start": 354700, "end": 357120}, {"text": ["[Continues singing in \"puu\"]"], "index": 59, "start": 357120, "end": 360340}, {"text": ["[Exhausted panting]"], "index": 60, "start": 360340, "end": 365970}, {"text": ["You can tell that we are now", "reaching a much higher elevation,"], "index": 61, "start": 365970, "end": 369680}, {"text": ["because the air is", "becoming so much thinner."], "index": 62, "start": 369680, "end": 372470}, {"text": ["[Exhausted panting]"], "index": 63, "start": 372470, "end": 373810}, {"text": ["Hey Umi! Fuu!", "You guys can't give up!"], "index": 64, "start": 373810, "end": 376680}, {"text": ["You actually still", "have energy left?"], "index": 65, "start": 377190, "end": 379770}, {"text": ["Aren't you tired, Miss Hikaru?"], "index": 66, "start": 380150, "end": 382230}, {"text": ["Yeah, of course it's hard!"], "index": 67, "start": 383110, "end": 384440}, {"text": ["But what's driving", "me on is that both you"], "index": 68, "start": 384440, "end": 386453}, {"text": ["guys were able to", "revive Rune Gods already!"], "index": 69, "start": 386477, "end": 388490}, {"text": ["It's my turn to", "find the Rune God!"], "index": 70, "start": 388700, "end": 390740}, {"text": ["I have to do my best so that I'll be", "prepared when my time comes up."], "index": 71, "start": 390740, "end": 394330}, {"text": ["Remember what Ferio said?"], "index": 72, "start": 394990, "end": 396870}, {"text": ["He said according to the", "legends, there are three Rune Gods."], "index": 73, "start": 396870, "end": 399790}, {"text": ["Three Rune Gods?"], "index": 74, "start": 399790, "end": 401210}, {"text": ["Oh yeah.", "I guess that must mean there's"], "index": 75, "start": 401210, "end": 403130}, {"text": ["supposed to be one", "Rune God for each of us."], "index": 76, "start": 403154, "end": 405380}, {"text": ["In that case, I would expect", "that the third Rune God"], "index": 77, "start": 405380, "end": 408098}, {"text": ["that we encounter would", "be reserved for Miss Hikaru."], "index": 78, "start": 408122, "end": 410840}, {"text": ["Yeah!", "I'm totally sure that's right!"], "index": 79, "start": 410840, "end": 413100}, {"text": ["And that must be the reason", "why Princess Emeraude"], "index": 80, "start": 413100, "end": 415776}, {"text": ["summoned the three", "of us here to Cephiro."], "index": 81, "start": 415800, "end": 418140}, {"text": ["Then all we need to", "do is find the third Rune"], "index": 82, "start": 418140, "end": 420645}, {"text": ["God, and we can", "become the Magic Knights!"], "index": 83, "start": 420669, "end": 423060}, {"text": ["As Miss Hikaru says, the three of", "us must do our best and not give up."], "index": 84, "start": 423060, "end": 427530}, {"text": ["- Let's go!", "- Okay!"], "index": 85, "start": 427530, "end": 429780}, {"text": ["[Frightened \"puu\"s]"], "index": 86, "start": 432030, "end": 435410}, {"text": ["Is something wrong, Mokona?"], "index": 87, "start": 435410, "end": 437410}, {"text": ["Puu puu, puu-puu puu puu."], "index": 88, "start": 437410, "end": 439790}, {"text": ["[Chewing squelches]"], "index": 89, "start": 439790, "end": 444500}, {"text": ["A monster!"], "index": 90, "start": 444500, "end": 445710}, {"text": ["Oh my gosh, it looks like it's", "eating something down there!"], "index": 91, "start": 445710, "end": 448630}, {"text": ["[Menacing growl]"], "index": 92, "start": 449800, "end": 452010}, {"text": ["It seems that it's eating", "some sort of animal."], "index": 93, "start": 452010, "end": 454680}, {"text": ["Yeah, it looks like it."], "index": 94, "start": 454680, "end": 456560}, {"text": ["[Angry growl]"], "index": 95, "start": 456560, "end": 458270}, {"text": ["And now it looks, as", "though Mister Monster"], "index": 96, "start": 458270, "end": 460508}, {"text": ["might be getting ready", "for his next course."], "index": 97, "start": 460532, "end": 462770}, {"text": ["[Angry screech]"], "index": 98, "start": 462770, "end": 465440}, {"text": ["[Startled shouting]"], "index": 99, "start": 467780, "end": 469490}, {"text": ["[Battle yell, magic hums]"], "index": 100, "start": 471030, "end": 474120}, {"text": ["[Battle shout]"], "index": 101, "start": 474120, "end": 477290}, {"text": ["[Gas hisses] [Startled shout]"], "index": 102, "start": 480870, "end": 482710}, {"text": ["- Miss Hikaru!", "- Hikaru!"], "index": 103, "start": 482710, "end": 484830}, {"text": ["[Pained groan] My... my eyes!"], "index": 104, "start": 484830, "end": 488630}, {"text": ["[Magic hums] Watch out, Hikaru!"], "index": 105, "start": 492880, "end": 495510}, {"text": ["[Battle shout]"], "index": 106, "start": 495510, "end": 498310}, {"text": ["[Angry screech]"], "index": 107, "start": 503060, "end": 504850}, {"text": ["This is one creepy creature!"], "index": 108, "start": 504850, "end": 506860}, {"text": ["Okay, let's finish this!"], "index": 109, "start": 506860, "end": 508610}, {"text": ["Umi, wait!", "This one's really powerful!"], "index": 110, "start": 508610, "end": 510820}, {"text": ["[Fearsome screeching]"], "index": 111, "start": 510820, "end": 513240}, {"text": ["[Startled shout, groan]"], "index": 112, "start": 513240, "end": 516780}, {"text": ["[Alarmed shout, pained grunt]"], "index": 113, "start": 519290, "end": 521290}, {"text": ["- Miss Umi!", "- Umi!"], "index": 114, "start": 522500, "end": 524330}, {"text": ["[Pained groaning]"], "index": 115, "start": 525580, "end": 527460}, {"text": ["[Alarmed shout]"], "index": 116, "start": 527460, "end": 529880}, {"text": ["[Frightened screams]"], "index": 117, "start": 530460, "end": 533090}, {"text": ["Umi, no!"], "index": 118, "start": 534090, "end": 535550}, {"text": ["- Flame Arro- - Wait!"], "index": 119, "start": 535550, "end": 537430}, {"text": ["You might hurt Miss Umi", "if you use your magic now!"], "index": 120, "start": 537430, "end": 540260}, {"text": ["But uh..."], "index": 121, "start": 540260, "end": 541810}, {"text": ["We must bring that to Miss Umi."], "index": 122, "start": 542560, "end": 544480}, {"text": ["Oh."], "index": 123, "start": 544480, "end": 545940}, {"text": ["[Bubbles, splashes] [Magic hums]"], "index": 124, "start": 548150, "end": 553150}, {"text": ["Oh! Her sword!"], "index": 125, "start": 553900, "end": 555200}, {"text": ["What do you thinks going on?"], "index": 126, "start": 555200, "end": 557280}, {"text": ["We have no other choice.", "[Magic hums]"], "index": 127, "start": 557280, "end": 560120}, {"text": ["Miss Umi! Use this!"], "index": 128, "start": 561990, "end": 563910}, {"text": ["[Strained grunt, Startled shout]"], "index": 129, "start": 563910, "end": 568630}, {"text": ["[Heavy panting] Umi!"], "index": 130, "start": 574630, "end": 578760}, {"text": ["[Menacing screech]"], "index": 131, "start": 580560, "end": 582720}, {"text": ["[Screeches]"], "index": 132, "start": 586390, "end": 588350}, {"text": ["[Frightened scream]"], "index": 133, "start": 592530, "end": 594570}, {"text": ["[Alarmed shouting, grunts]"], "index": 134, "start": 597280, "end": 599660}, {"text": ["- [Pained groans] Umi!", "- Hey!"], "index": 135, "start": 599660, "end": 602370}, {"text": ["- Are you alright?", "- I think so!"], "index": 136, "start": 602370, "end": 604910}, {"text": ["Hey Fuu. Your sword.", "Isn't it really heavy?"], "index": 137, "start": 607540, "end": 610670}, {"text": ["Not at all.", "It is as light as a feather."], "index": 138, "start": 610670, "end": 613460}, {"text": ["Can I borrow it for a second?"], "index": 139, "start": 613460, "end": 615720}, {"text": ["- Sure.", "- Whoa! [Startled shout]"], "index": 140, "start": 615720, "end": 618180}, {"text": ["[Heavy clang]"], "index": 141, "start": 618720, "end": 620550}, {"text": ["This is extremely peculiar. The", "sword feels extraordinarily light to me."], "index": 142, "start": 620550, "end": 624850}, {"text": ["No way!", "It's the heaviest thing in the world!"], "index": 143, "start": 624850, "end": 627810}, {"text": ["What about yours?"], "index": 144, "start": 628640, "end": 630650}, {"text": ["That's right, I dropped it."], "index": 145, "start": 633020, "end": 635110}, {"text": ["It has returned to", "it's previous form."], "index": 146, "start": 638490, "end": 641160}, {"text": ["I think I'm starting to get it."], "index": 147, "start": 641160, "end": 643080}, {"text": ["Huh?"], "index": 148, "start": 643080, "end": 644120}, {"text": ["Just before, when Fuu", "tried to pick up your sword"], "index": 149, "start": 644120, "end": 646568}, {"text": ["it turned into something", "that looked like water."], "index": 150, "start": 646592, "end": 649040}, {"text": ["What are you talking about?"], "index": 151, "start": 649040, "end": 650330}, {"text": ["This must mean that these weapons have", "been made especially for each one of us."], "index": 152, "start": 650330, "end": 654550}, {"text": ["Weapons made", "especially for each of us?"], "index": 153, "start": 655170, "end": 658130}, {"text": ["And they've changed a lot, you know?", "From when we first got them from Presea."], "index": 154, "start": 658130, "end": 662470}, {"text": ["[Magic ripples]"], "index": 155, "start": 683711, "end": 686469}, {"text": ["[Magic ripples]"], "index": 156, "start": 695290, "end": 698670}, {"text": ["[Magic ripples]"], "index": 157, "start": 702510, "end": 705050}, {"text": ["[Magic ripples, shatters]"], "index": 158, "start": 708100, "end": 712350}, {"text": ["Oh! Our armor has evolved again!"], "index": 159, "start": 721150, "end": 724160}, {"text": ["Our swords too!"], "index": 160, "start": 724910, "end": 726280}, {"text": ["Our swords are evolving also."], "index": 161, "start": 726280, "end": 728790}, {"text": ["Puu-puu puu-puu puu!"], "index": 162, "start": 730160, "end": 732750}, {"text": ["All three of us have", "matching outfits!"], "index": 163, "start": 732750, "end": 735710}, {"text": ["We must never forget that Presea gave", "her life to make these weapons for us."], "index": 164, "start": 737000, "end": 741550}, {"text": ["We gotta do our best!"], "index": 165, "start": 741550, "end": 743470}, {"text": ["Mm-hmm!"], "index": 166, "start": 743470, "end": 745180}, {"text": ["By the way, did you happen to notice the", "person who defeated that monster for us?"], "index": 167, "start": 747760, "end": 752270}, {"text": ["That's right!", "We forgot to thank him!"], "index": 168, "start": 752270, "end": 755150}, {"text": ["That's him right there!"], "index": 169, "start": 768950, "end": 770790}, {"text": ["Hello there! We need to thank", "you for saving our friend Umi!"], "index": 170, "start": 786390, "end": 790180}, {"text": ["I wonder if something's wrong."], "index": 171, "start": 792390, "end": 794560}, {"text": ["Perhaps he is rather shy."], "index": 172, "start": 794560, "end": 796690}, {"text": ["Something's strange though."], "index": 173, "start": 796690, "end": 798230}, {"text": ["Thank you very much", "for saving my life just now!"], "index": 174, "start": 798230, "end": 800780}, {"text": ["[Alarmed shout]"], "index": 175, "start": 805860, "end": 807660}, {"text": ["[Strained groan, shouts]"], "index": 176, "start": 809280, "end": 812700}, {"text": ["- [Pained shout]", "- Umi!"], "index": 177, "start": 812870, "end": 815160}, {"text": ["[Strained grunts]"], "index": 178, "start": 819790, "end": 823880}, {"text": ["Miss Hikaru!"], "index": 179, "start": 823880, "end": 825380}, {"text": ["Okay, who are you!?"], "index": 180, "start": 836810, "end": 839560}, {"text": ["Swordmaster Lafarga."], "index": 181, "start": 841230, "end": 843940}, {"text": ["Swordmaster?"], "index": 182, "start": 843940, "end": 845150}, {"text": ["I defeat all enemies", "using only my sword."], "index": 183, "start": 845150, "end": 848530}, {"text": ["Are you one of Zagato's minions?"], "index": 184, "start": 848530, "end": 850160}, {"text": ["Why are you attacking us?"], "index": 185, "start": 850160, "end": 851660}, {"text": ["Because my mission is the", "annihilation of the Magic Knights."], "index": 186, "start": 851660, "end": 855750}, {"text": ["So, why did you save me", "from that monster before?"], "index": 187, "start": 855750, "end": 858920}, {"text": ["If that monster had killed you, I would", "be unable to accomplish my mission."], "index": 188, "start": 859790, "end": 864380}, {"text": ["That makes a lot of sense!"], "index": 189, "start": 864380, "end": 866010}, {"text": ["[Furious battle shout]"], "index": 190, "start": 866920, "end": 869300}, {"text": ["[Frightened screams]"], "index": 191, "start": 870010, "end": 872180}, {"text": ["Look!", "What happened to the ground?"], "index": 192, "start": 872510, "end": 874560}, {"text": ["He didn't touch it, yet", "it crumbled like sand!"], "index": 193, "start": 874560, "end": 877850}, {"text": ["Wind pressure!", "It's the wind pressure from his sword!"], "index": 194, "start": 877850, "end": 880650}, {"text": ["[Angry growl]"], "index": 195, "start": 880650, "end": 882520}, {"text": ["[Alarmed screams]"], "index": 196, "start": 882520, "end": 885230}, {"text": ["[Startled screams]"], "index": 197, "start": 885593, "end": 890116}, {"text": ["Ugh! It's just no use!", "He's too powerful!"], "index": 198, "start": 892870, "end": 895370}, {"text": ["[Battle shout]"], "index": 199, "start": 896120, "end": 898330}, {"text": ["[Startled gasps]"], "index": 200, "start": 898330, "end": 899920}, {"text": ["[Frightened screams]"], "index": 201, "start": 899920, "end": 901330}, {"text": ["Hey Umi! Fuu! Are you alright?"], "index": 202, "start": 901330, "end": 903540}, {"text": ["[Pained groans]"], "index": 203, "start": 906840, "end": 910930}, {"text": ["[Battle shout]"], "index": 204, "start": 910930, "end": 913350}, {"text": ["Hey you guys! Watch out!"], "index": 205, "start": 914600, "end": 916600}, {"text": ["[Strained groan]"], "index": 206, "start": 916600, "end": 919390}, {"text": ["[Startled gasps]"], "index": 207, "start": 919390, "end": 921480}, {"text": ["[Exhausted panting]"], "index": 208, "start": 921690, "end": 927280}, {"text": ["My mission is the annihilation", "of the Magic Knights."], "index": 209, "start": 928690, "end": 932780}, {"text": ["If I don't stand my ground,", "his attack will hit Umi and Fuu."], "index": 210, "start": 933200, "end": 937160}, {"text": ["[Battle shout]"], "index": 211, "start": 938620, "end": 940960}, {"text": ["Is that all you can do!?"], "index": 212, "start": 941330, "end": 942670}, {"text": ["Run for it, Hikaru!"], "index": 213, "start": 942670, "end": 944250}, {"text": ["You must save yourself!"], "index": 214, "start": 944250, "end": 946250}, {"text": ["[Strained groans]"], "index": 215, "start": 946250, "end": 949170}, {"text": ["[Exhausted panting]"], "index": 216, "start": 950300, "end": 954680}, {"text": ["I'm not giving up!"], "index": 217, "start": 962310, "end": 964690}, {"text": ["The three of us...", "the three of us! Umi, Fuu and I."], "index": 218, "start": 965020, "end": 968820}, {"text": ["Together we're gonna", "become the Magic Knights."], "index": 219, "start": 969190, "end": 973320}, {"text": ["And we're gonna", "go back to Tokyo!"], "index": 220, "start": 974410, "end": 977870}, {"text": ["[Magic hums and crackles]"], "index": 221, "start": 977987, "end": 981685}, {"text": ["Miss Hikaru!"], "index": 222, "start": 981710, "end": 983500}, {"text": ["Hikaru, use magic!"], "index": 223, "start": 983750, "end": 985920}, {"text": ["My opponent is a swordsman.", "I have to fight him with a sword."], "index": 224, "start": 986250, "end": 989710}, {"text": ["I have to make sure that I become a", "Magic Knight along with my best friends,"], "index": 225, "start": 989710, "end": 993510}, {"text": ["and the three of us will", "save Princess Emeraude!"], "index": 226, "start": 993510, "end": 996550}, {"text": ["Princess Emeraude."], "index": 227, "start": 996550, "end": 998180}, {"text": ["And we'll save Cephiro too!"], "index": 228, "start": 998180, "end": 1000640}, {"text": ["Princess."], "index": 229, "start": 1000640, "end": 1002310}, {"text": ["[Pained groans]"], "index": 230, "start": 1002600, "end": 1006560}, {"text": ["What? What's going on?"], "index": 231, "start": 1006560, "end": 1008480}, {"text": ["[Magic buzzes, Lafarga groans]"], "index": 232, "start": 1008480, "end": 1010900}, {"text": ["- [Startled shout]", "- [Battle shout]"], "index": 233, "start": 1010900, "end": 1014030}, {"text": ["[Repeated angry shouting]"], "index": 234, "start": 1014030, "end": 1017870}, {"text": ["[Strained groans]"], "index": 235, "start": 1017870, "end": 1020450}, {"text": ["[Pained groan]"], "index": 236, "start": 1020450, "end": 1022250}, {"text": ["What's the matter with you!?"], "index": 237, "start": 1022250, "end": 1024040}, {"text": ["Did you do something", "to Princess Emeraude!?"], "index": 238, "start": 1024040, "end": 1026630}, {"text": ["Ugh, Princess..."], "index": 239, "start": 1026630, "end": 1028540}, {"text": ["Lafarga, please help me!", "Lafarga!"], "index": 240, "start": 1028840, "end": 1032260}, {"text": ["Princess Emeraude!"], "index": 241, "start": 1032970, "end": 1034760}, {"text": ["[Forceful yell]"], "index": 242, "start": 1034760, "end": 1037010}, {"text": ["[Startled gasp]"], "index": 243, "start": 1044597, "end": 1046125}, {"text": ["[Exhausted panting]"], "index": 244, "start": 1046150, "end": 1048770}, {"text": ["[Battle shout]"], "index": 245, "start": 1052190, "end": 1055950}, {"text": ["[Strained grunts, shouts]"], "index": 246, "start": 1055950, "end": 1059580}, {"text": ["[Determined grunt]"], "index": 247, "start": 1063487, "end": 1065322}, {"text": ["Princess Emeraude!"], "index": 248, "start": 1065830, "end": 1067960}, {"text": ["[Battle shout]"], "index": 249, "start": 1073210, "end": 1076300}, {"text": ["[Booming explosion]"], "index": 250, "start": 1076880, "end": 1078300}, {"text": ["[Squelches] [Pained scream]"], "index": 251, "start": 1078300, "end": 1081640}, {"text": ["- [Choking gasp]", "- [Frustrated growl]"], "index": 252, "start": 1082260, "end": 1089190}, {"text": ["Princess Emeraude!"], "index": 253, "start": 1100450, "end": 1102990}, {"text": ["[Magic whooshes] [Pained shout]"], "index": 254, "start": 1104330, "end": 1106790}, {"text": ["Captain of the Guard Lafarga.", "I acknowledge"], "index": 255, "start": 1108870, "end": 1111779}, {"text": ["that you are a faithful", "servant to your master."], "index": 256, "start": 1111803, "end": 1115130}, {"text": ["[Pained groan] Zagato!", "Why are you trying to take the Princess?"], "index": 257, "start": 1115130, "end": 1119890}, {"text": ["Tell me what you're", "planning to do with her!"], "index": 258, "start": 1120090, "end": 1122430}, {"text": ["Unfortunately, it", "does not concern you."], "index": 259, "start": 1122430, "end": 1125770}, {"text": ["[Both groaning]"], "index": 260, "start": 1129520, "end": 1134940}, {"text": ["[Magic ripples]"], "index": 261, "start": 1135230, "end": 1138200}, {"text": ["[Pained screaming]"], "index": 262, "start": 1138200, "end": 1143030}, {"text": ["[Magic whooshes,", "pained screaming]"], "index": 263, "start": 1145330, "end": 1148960}, {"text": ["[Startled gasp] Lafarga!"], "index": 264, "start": 1148960, "end": 1151170}, {"text": ["Lafarga! Lafarga!"], "index": 265, "start": 1152080, "end": 1155500}, {"text": ["[Pained groans] [Sword clatters]"], "index": 266, "start": 1156800, "end": 1160470}, {"text": ["[Flames crackle]"], "index": 267, "start": 1160495, "end": 1162810}, {"text": ["A weapon just for me. My sword just", "turned itself into a ball of flames."], "index": 268, "start": 1165760, "end": 1170560}, {"text": ["Hey, did you just see that?"], "index": 269, "start": 1171100, "end": 1172770}, {"text": ["Her sword emits flames when", "anyone other than she handles it."], "index": 270, "start": 1172770, "end": 1176780}, {"text": ["[Pained groans]"], "index": 271, "start": 1178110, "end": 1181780}, {"text": ["Where... where am I?"], "index": 272, "start": 1181910, "end": 1183620}, {"text": ["[Determined huff]"], "index": 273, "start": 1183870, "end": 1185450}, {"text": ["Where is she!? Do you know what", "has happened to Princess Emeraude?"], "index": 274, "start": 1186200, "end": 1189620}, {"text": ["[Surprised gasp]"], "index": 275, "start": 1189620, "end": 1191210}, {"text": ["[Pained groan]"], "index": 276, "start": 1191670, "end": 1194130}, {"text": ["I must save Princess Emeraude!"], "index": 277, "start": 1194130, "end": 1196210}, {"text": ["Save the princess? You mean to", "say you're not one of Zagato's minions?"], "index": 278, "start": 1196630, "end": 1200630}, {"text": ["The Princess..."], "index": 279, "start": 1201430, "end": 1203090}, {"text": ["I serve and protect Princess", "Emeraude, the Pillar of Cephiro."], "index": 280, "start": 1203470, "end": 1206890}, {"text": ["My job is to guard", "and protect the princess"], "index": 281, "start": 1207180, "end": 1209471}, {"text": ["so that her prayers", "will never be interrupted."], "index": 282, "start": 1209495, "end": 1212060}, {"text": ["So that peace and order", "will always be preserved."], "index": 283, "start": 1212060, "end": 1214900}, {"text": ["I tried to stop Lord", "Zagato from taking her,"], "index": 284, "start": 1216320, "end": 1218980}, {"text": ["But, I..."], "index": 285, "start": 1218980, "end": 1220610}, {"text": ["[Startled gasp] How did you", "get those wounds? Was it me?"], "index": 286, "start": 1220860, "end": 1224280}, {"text": ["It's alright.", "You weren't responsible"], "index": 287, "start": 1224570, "end": 1226487}, {"text": ["because you were being", "controlled by Zagato."], "index": 288, "start": 1226511, "end": 1228910}, {"text": ["So please, don't worry."], "index": 289, "start": 1228910, "end": 1231160}, {"text": ["Hello over there!"], "index": 290, "start": 1232120, "end": 1233500}, {"text": ["If he's not one of", "Zagato's minions,do you"], "index": 291, "start": 1233500, "end": 1235513}, {"text": ["think he could help", "us get out of here?"], "index": 292, "start": 1235537, "end": 1237500}, {"text": ["Ahh..."], "index": 293, "start": 1237500, "end": 1239090}, {"text": ["Lafarga, here."], "index": 294, "start": 1243930, "end": 1245680}, {"text": ["I'm sorry."], "index": 295, "start": 1249600, "end": 1251270}, {"text": ["Oh, I'm sorry about the flames."], "index": 296, "start": 1251930, "end": 1254350}, {"text": ["You didn't get burned?"], "index": 297, "start": 1254350, "end": 1255810}, {"text": ["Hmm?"], "index": 298, "start": 1255810, "end": 1257480}, {"text": ["Do not worry about me."], "index": 299, "start": 1258690, "end": 1260530}, {"text": ["[Relieved gasp]"], "index": 300, "start": 1260530, "end": 1262150}, {"text": ["If you don't mind,", "who are you three?"], "index": 301, "start": 1262150, "end": 1264530}, {"text": ["The three of us were summoned", "here from Tokyo by Princess Emeraude."], "index": 302, "start": 1264530, "end": 1268160}, {"text": ["We're going to become", "the Magic Knights."], "index": 303, "start": 1268160, "end": 1270620}, {"text": ["The Magic Knights?", "The Legendary Magic Knights? Is it true?"], "index": 304, "start": 1270620, "end": 1275210}, {"text": ["We haven't made", "it quite yet, though."], "index": 305, "start": 1275210, "end": 1277210}, {"text": ["We're almost there."], "index": 306, "start": 1277210, "end": 1278630}, {"text": ["All we have to do is revive", "one more Rune God and"], "index": 307, "start": 1278630, "end": 1281453}, {"text": ["we'll finally be able to", "rescue Princess Emeraude."], "index": 308, "start": 1281477, "end": 1284300}, {"text": ["I see. You three are the ones."], "index": 309, "start": 1285050, "end": 1288050}, {"text": ["What are you planning to do now?"], "index": 310, "start": 1288720, "end": 1290640}, {"text": ["Only those from another world", "can become Magic Knights."], "index": 311, "start": 1290640, "end": 1293890}, {"text": ["However, I will now", "commence my quest to search"], "index": 312, "start": 1293890, "end": 1296560}, {"text": ["out and rescue Princess", "Emeraude as well."], "index": 313, "start": 1296584, "end": 1299020}, {"text": ["I thank you from the", "bottom of my heart."], "index": 314, "start": 1299020, "end": 1301530}, {"text": ["I have now been set free from the", "nightmare of Zagato's evil magic spell."], "index": 315, "start": 1301530, "end": 1305700}, {"text": ["I know we will meet again."], "index": 316, "start": 1305700, "end": 1307570}, {"text": ["Lafarga!"], "index": 317, "start": 1310370, "end": 1311450}, {"text": ["- Mister Lafarga!", "- Lafarga!"], "index": 318, "start": 1311450, "end": 1313870}, {"text": ["He's already gone."], "index": 319, "start": 1313870, "end": 1315790}, {"text": ["Hey you guys!", "It's time for us to get a move on, too!"], "index": 320, "start": 1315790, "end": 1319210}, {"text": ["The third Rune", "God is waiting for us!"], "index": 321, "start": 1319210, "end": 1321460}, {"text": ["Yeah!"], "index": 322, "start": 1321460, "end": 1322710}, {"text": ["Puu-puu, puu-puu!"], "index": 323, "start": 1322710, "end": 1325050}, {"text": ["We've got to go save", "Princess Emeraude!"], "index": 324, "start": 1325260, "end": 1328010}, {"text": ["Who is it today?"], "index": 325, "start": 1461270, "end": 1462770}, {"text": ["Today, it's Mokona!"], "index": 326, "start": 1467020, "end": 1468940}, {"text": ["Puu puu, puu-puu-puu, puu-puu!", "Puuuu!"], "index": 327, "start": 1469730, "end": 1473990}]